{"moogle": {"min": [["폼폼푸린", "1133657"], ["김보라", "1055068"], ["오란", "1025143"], ["김호랑", "1016390"], ["타타푸", "861969"], ["나르시냐크'", "801626"], ["메이드인차이나", "800050"], ["슈크림멜", "784713"], ["인생최후의지진강타", "773742"], ["서늘우", "748001"], ["연오구", "747794"], ["폴라밍고", "736648"], ["취급", "733904"], ["이단류", "731986"], ["프푸", "728451"], ["리브나", "711589"], ["뉴냐", "701133"], ["개기찬", "674945"], ["파르베", "557785"], ["백도언", "513979"], ["월급좀도둑", "417695"], ["뀨우는사랑이에요", "400115"], ["블루스탈", "392169"], ["현화", "268029"], ["도트'", "260449"], ["은페럿", "256954"], ["벅으", "249149"], ["인센드", "236606"], ["비오네", "226326"], ["후회", "226286"], ["킷캣녹차", "215523"], ["혼인", "213775"], ["호머장", "213555"], ["야전치유진", "213431"], ["으먓", "210028"], ["맘바", "206205"], ["마키엘라", "203625"], ["한조윤", "202097"], ["숲'", "198980"], ["신월설희", "198448"], ["Mackerel", "195791"], ["곰곰상야캐요", "192217"], ["투명종이", "190336"], ["Espoir", "188239"], ["아로니아", "178002"], ["시연화", "175163"], ["에린시", "167990"], ["발렌티앙", "156521"], ["메지아", "155915"], ["주유소사장님", "150098"], ["카디디", "148449"], ["헤라씨", "143746"], ["대작전", "136664"], ["Nunnu", "135885"], ["Snowblast", "134509"], ["얼음골사과", "132948"], ["레빌", "127553"], ["Austerity", "121895"], ["Immense", "121701"], ["주호민", "118510"], ["시루묵", "113811"], ["Sidepark", "111816"], ["탈탈이", "104764"], ["김라드", "102611"], ["위리슈티팡", "101774"], ["Elwin", "100913"], ["은유월", "100102"], ["직선", "99891"], ["랑먕묭", "98587"], ["헤리", "97785"], ["모안", "96601"], ["다미곰", "95646"], ["치즈냐", "92300"], ["레쿠쟈", "90943"], ["짱나", "88634"], ["헤르나", "88516"], ["케렌디아", "87781"], ["Reize", "87765"], ["아따비키랑께", "84737"], ["벨라엔", "83671"], ["봄향", "83509"], ["담유", "81727"], ["흑버들", "79798"], ["태초의어릿광대거상", "79292"], ["새겨울", "78755"], ["단순", "76273"], ["에티프", "75437"], ["몽상가", "74736"], ["일련화", "73681"], ["궤적", "72579"], ["아서울프", "71548"], ["테네브레아", "70318"], ["쓱싹쓱싹김열무", "65551"], ["별사탕체", "65356"], ["지바냥", "64835"], ["루엘레스", "64572"], ["호짜이", "62884"], ["봘을작살내", "62074"], ["바보같은흰색", "59196"], ["아시오", "58644"]], "btn": [["대왕슈크림", "1458102"], ["랑이", "1397438"], ["세헤라", "1187513"], ["문학곰", "1098548"], ["온도", "1033110"], ["서서아", "1004503"], ["카베이", "975895"], ["사피", "940541"], ["루가딘'", "935358"], ["세피르", "930424"], ["다람", "930277"], ["연인", "919435"], ["인테노", "914120"], ["Gladio", "910255"], ["멍새우", "879489"], ["야매힐러", "701307"], ["렐리엔", "610649"], ["하이노량쟈", "561609"], ["백수시켜줘", "526053"], ["가류", "501049"], ["현재", "460983"], ["하슈크", "416656"], ["틀니", "415088"], ["나나헨", "413886"], ["메이브이", "404487"], ["제키단", "342816"], ["바닐라푸딩", "300610"], ["대학꾜등로끔", "294591"], ["키르케", "241604"], ["디마", "235724"], ["Austerity", "229345"], ["극단", "200954"], ["흠을", "190210"], ["Immense", "188170"], ["바름", "184612"], ["유령펠", "184592"], ["초코바비", "184268"], ["유키노하나", "181765"], ["치킨이삐", "179994"], ["흑성", "178558"], ["메론프라페", "173610"], ["정육면체", "162876"], ["사랑은전진", "157225"], ["가로수길아래", "145017"], ["리드멜", "141175"], ["하견", "138957"], ["테르테지아", "134444"], ["휘서", "130829"], ["아주대스나이퍼", "130619"], ["김메밀묵", "130093"], ["토리님", "129453"], ["황야의토끼", "127707"], ["탱의한수", "119308"], ["리오센트", "117176"], ["바니르", "107983"], ["토르덴크", "106798"], ["박도현", "105211"], ["로말레오사우루스", "104241"], ["은날치", "103294"], ["블릴리언트", "102453"], ["시루묵", "101303"], ["이레니아", "100492"], ["파르헌", "100000"], ["둠칫두둠칫", "95854"], ["마론", "90655"], ["비오네", "89436"], ["쬬꼬보", "86944"], ["아기상어뚜루루", "86606"], ["리크", "82693"], ["챠오'", "82151"], ["멜라민", "81760"], ["캐러멜", "80306"], ["츠키는달", "76267"], ["은페럿", "75946"], ["직선", "74367"], ["믹믹", "73419"], ["벨레로폰", "73033"], ["하얀떡볶이", "72864"], ["타짜점성김푹고", "71689"], ["미드미코테", "71542"], ["유제리안", "67649"], ["나티", "67479"], ["김사비", "66887"], ["반혁", "64818"], ["집에가자진진자라", "64128"], ["중원", "63762"], ["아치킨먹고싶다", "61478"], ["톈의", "59978"], ["독고필태", "59338"], ["다솜너울", "59201"], ["고매님", "58236"], ["해로운파랑새", "57475"], ["토로롱", "57083"], ["헐이계인비너스", "56404"], ["발디프", "55174"], ["디디오", "54568"], ["도경수", "54080"], ["하닌", "53514"], ["별사탕체", "53348"], ["쪼삼치", "52954"]], "fsh": [["공식", "2400581"], ["안테카니스", "2117541"], ["작은'페뤼코스", "2055559"], ["갑배", "1732847"], ["뎅쥐", "1652561"], ["리스올리버", "1644940"], ["키넨", "1640000"], ["쿠뽀", "1614090"], ["Morphine", "1591131"], ["자중해라", "1471415"], ["Esilia", "1448805"], ["청산호", "1420930"], ["맹격", "1418592"], ["토라토라", "1408248"], ["에랄드", "1360891"], ["레고피규어", "1360705"], ["버질", "1348598"], ["리파인", "1331324"], ["루나링", "966208"], ["쟈몽몽", "820000"], ["랴리", "651613"], ["카우사", "591448"], ["라일렌", "437688"], ["홍조'", "423575"], ["프레센", "414436"], ["열백", "392607"], ["백조", "345670"], ["프린스송", "331510"], ["로말레오사우루스", "318371"], ["프늉", "313998"], ["럴러", "300000"], ["푹씬", "291532"], ["마다루", "283046"], ["땨님", "270097"], ["생꽁", "269867"], ["환여운", "265953"], ["크리산타", "232001"], ["리난", "213840"], ["쿤님", "200520"], ["Wornjs", "197852"], ["례아", "193684"], ["타루젠", "183272"], ["꼬순내", "181263"], ["하파", "174524"], ["리기두스", "167185"], ["백설설탕", "156260"], ["카뇨'", "151577"], ["모티별", "140880"], ["하서윤'", "136377"], ["써르", "132805"], ["로딩도와줘", "128816"], ["Jade", "127381"], ["베니모", "123475"], ["교재비", "123274"], ["섭현", "122375"], ["바닐라번", "119772"], ["별은하", "119558"], ["김의원", "118357"], ["히주히죽", "114329"], ["쭈코", "113535"], ["냐메", "111364"], ["네테", "105522"], ["히베르나", "104821"], ["일곡", "103643"], ["톄시", "101022"], ["로트에이딘", "100556"], ["피피로즈", "96099"], ["잇트스포", "95693"], ["아스밴더", "94752"], ["우애웅", "93409"], ["코나세", "91744"], ["상한복숭아", "89309"], ["칭송", "87677"], ["대통령", "86196"], ["셰이룬", "84966"], ["불용", "82926"], ["키쟌", "82262"], ["산'", "81697"], ["울다하풍의'모험가", "81597"], ["장곡강", "80078"], ["렌시아", "78956"], ["빈칸", "76956"], ["김못찌", "76667"], ["시루묵", "75737"], ["Defined", "74750"], ["실시아", "72768"], ["마쿠챤", "72501"], ["류드", "68083"], ["이서누", "67984"], ["유가", "64130"], ["녹차초콜릿", "63763"], ["Lozen", "61695"], ["Caitsith", "61638"], ["쌈자", "58227"], ["짱짱", "56857"], ["헤라씨", "56756"], ["뉴감귤", "52887"], ["렙삐", "52748"], ["쵸코맛있는우유", "52102"], ["적빛연고", "51436"]], "crp": [["뮤즈", "2855568"], ["낭인", "2070139"], ["김루인", "1536194"], ["크림치즈타르트", "1523119"], ["연히'", "1479490"], ["림녕", "1428864"], ["샤먼", "1409369"], ["라임맛쿠키", "1082043"], ["엘체", "1055542"], ["클로데르", "912606"], ["명륜", "905820"], ["시뤄", "843679"], ["백애", "778081"], ["셰아트", "721487"], ["바니르", "503427"], ["쌈자", "413524"], ["째기", "332208"], ["유피네", "219422"], ["사모니안", "172133"], ["멜라민", "135333"], ["디네", "117580"], ["김카루", "116681"], ["주전자껍데기", "114030"], ["다란", "113336"], ["쿠로냐", "111864"], ["독신", "106795"], ["뽐빛", "104902"], ["지한울", "101301"], ["문학곰", "97939"], ["벨레로폰", "86125"], ["꾸댕", "77220"], ["브룬힐더", "76870"], ["디디오", "68557"], ["길안내하는친구", "65522"], ["유메뀨이", "58620"], ["도경수", "57930"], ["칸티에", "57908"], ["설양", "51891"], ["고귀한냥이꼬리", "47897"], ["태룡", "42864"], ["옹옹이", "35818"], ["꿈빛", "33554"], ["엣쓔", "33530"], ["뉴하이", "33170"], ["욘욘슨", "32371"], ["교재비", "32361"], ["녹차곰돌이", "30891"], ["사뿐콩콩", "27842"], ["욜님", "26080"], ["렴땅", "25746"], ["우혼", "25059"], ["청혁", "24828"], ["김고", "23805"], ["톈의", "23680"], ["주은택", "22136"], ["쪼삼치", "21719"], ["프레센", "21653"], ["고양이여우", "21651"], ["초봄봄", "21012"], ["토로롱", "20711"], ["깨빵", "19938"], ["애봉", "19771"], ["설다향", "19730"], ["김플루", "19495"], ["번뇌목사", "19350"], ["자희", "19080"], ["Tirril", "16703"], ["안식", "15420"], ["산애", "15309"], ["눈물은모르게", "14494"], ["써니", "14010"], ["네잎클로버", "13507"], ["뚜뚠요정", "13070"], ["금목서", "13033"], ["샐리", "12630"], ["대학꾜등로끔", "12612"], ["태초의어릿광대거상", "12592"], ["랴리", "12585"], ["Lhggggg", "11865"], ["올파", "11822"], ["철컹철컹", "11567"], ["폰다프", "11075"], ["에이바", "10391"], ["토르덴크", "10338"], ["링뽀", "9821"], ["하게", "9777"], ["은예성", "9605"], ["리그렛샤", "9138"], ["순월", "9094"], ["시계", "9090"], ["하이젠", "9020"], ["로그아웃", "8990"], ["류준", "8923"], ["테리피어", "8907"], ["셀케트", "8863"], ["정월사탄", "8781"], ["Chris", "8670"], ["남사윤", "8586"], ["지평선", "8569"], ["알빈", "8550"]], "bsm": [["페이타", "2480915"], ["샤른", "2005726"], ["제르빈", "1528478"], ["케네시스", "1281123"], ["안나아", "1022538"], ["아폴로의눈", "963085"], ["역린", "946041"], ["플렌비", "924511"], ["루스카브", "896075"], ["눈설아", "892044"], ["테베르데", "878380"], ["프로냥줍러", "840514"], ["체리타", "792656"], ["히세아", "786589"], ["애랑쓰", "780746"], ["파란적란운", "728643"], ["연탄", "720281"], ["돈들어손내놔", "711873"], ["먕찌", "681722"], ["꽁치파닥", "383459"], ["매진", "322511"], ["김쇠자", "294375"], ["냥귤", "217293"], ["책스초코", "203892"], ["핵카", "181263"], ["룯길", "178840"], ["비덴스", "164465"], ["메렌게", "162542"], ["Anael", "160507"], ["초승달", "127198"], ["베라'", "123869"], ["지바냥", "115762"], ["세뤼오", "115439"], ["예슬기", "115433"], ["챠뵤", "110503"], ["유이링", "109479"], ["교수", "96491"], ["하나바나", "95164"], ["화랑운", "95161"], ["Vespine", "90351"], ["올모", "87436"], ["타후티", "76060"], ["은시월", "70246"], ["Reize", "70158"], ["츠츠비", "67428"], ["답이없다", "62619"], ["Nkel", "60965"], ["라이블리", "58668"], ["가을나무", "56402"], ["랑고", "51340"], ["삼독", "50797"], ["Mauve", "49253"], ["Meridia", "46865"], ["레쿠쟈", "46138"], ["히루룬", "46020"], ["Arush", "38151"], ["영생도둑", "33137"], ["은유월", "32931"], ["구랭", "32642"], ["브룬힐더", "32310"], ["Amyre", "31864"], ["Saraqael", "31705"], ["녹차곰돌이", "30573"], ["입금시만능공", "29104"], ["구영", "28322"], ["패니트", "28251"], ["이보", "27904"], ["리멤버", "27758"], ["폴라밍고", "27448"], ["로크텐", "26695"], ["쥬이니", "24450"], ["삐염", "22129"], ["아슬란'", "20936"], ["례아", "20885"], ["리그렛샤", "20671"], ["엘라다", "19199"], ["디디오", "18995"], ["Reisi", "16830"], ["주님갑니다", "15500"], ["사나뭇잎", "15210"], ["Scik", "14794"], ["관영", "14642"], ["니에라", "13739"], ["무사도", "13603"], ["타타푸", "13437"], ["다별", "12990"], ["덕철", "12789"], ["챠유", "12732"], ["토노", "12547"], ["상한레몬밤", "12481"], ["Halrid", "12469"], ["하다레크", "11906"], ["Adelaides", "11903"], ["빗차", "11550"], ["궤적", "11546"], ["애기엄마", "11449"], ["하이젠", "10528"], ["타다시", "10469"], ["논나", "10441"], ["이노스", "10278"]], "arm": [["루엘레스", "2200000"], ["요조'", "1907717"], ["비냐냐", "1770498"], ["뉴비", "1234567"], ["뉴므뉴므", "1176587"], ["단하도", "1115939"], ["의욕'", "1069872"], ["햄릿", "1037595"], ["파와와", "1035147"], ["양파법사", "1021290"], ["말랑말랑마시멜로", "1020617"], ["초'", "1006346"], ["델리미트", "949298"], ["아라쿠모", "930959"], ["사모니안", "504170"], ["봘을작살내", "448870"], ["시엘렌", "438671"], ["루르", "433441"], ["쓱싹쓱싹김열무", "331195"], ["잘차려진한정식", "331014"], ["리멤버", "329066"], ["코우지", "277049"], ["카마엘", "205539"], ["온셈", "193579"], ["리샤라차", "164673"], ["세시얀", "159406"], ["윤형", "122058"], ["유리피", "105149"], ["여을", "97366"], ["Hwaya", "93605"], ["Diary", "92614"], ["왕개구리", "81029"], ["세르키리니", "78160"], ["라밍라밍", "75872"], ["모마모토", "64065"], ["도비는자유", "54150"], ["샤루민", "53953"], ["Jaebin", "53817"], ["벼걍", "51561"], ["Renne", "50831"], ["쩡아리", "50378"], ["화이트큐라소", "47161"], ["루르치시에", "42001"], ["모안", "42000"], ["Pn", "39610"], ["리'페", "39503"], ["모끄", "37704"], ["도카", "36102"], ["아서울프", "34968"], ["엘싸", "33890"], ["련찬", "32399"], ["태초의어릿광대거상", "32279"], ["구원의마왕'", "32134"], ["심미", "31544"], ["소일", "31424"], ["녹차곰돌이", "30109"], ["벨라엔", "29509"], ["릴리에르", "28840"], ["곡곡곡", "27243"], ["지서하", "26670"], ["심재", "24802"], ["아스터", "24682"], ["기기", "24002"], ["무견", "22295"], ["별난로", "20086"], ["이세이", "20035"], ["귤맛마이구미", "20000"], ["광팔식", "18568"], ["엘스'", "18111"], ["하이젠", "17320"], ["로그리얼", "16458"], ["늘찬", "16020"], ["하니", "15842"], ["연팡", "15416"], ["버레이즈", "15265"], ["도월", "15209"], ["크라이트엘", "15167"], ["Song", "14982"], ["엘라다", "14869"], ["Reize", "14657"], ["네테", "14563"], ["우리주인", "13944"], ["샤오무", "13756"], ["클로에루", "13704"], ["셰드챤", "13291"], ["공청'", "13260"], ["엘닛", "13251"], ["엘제", "12893"], ["코코메", "12828"], ["아세리안", "12770"], ["타등", "12425"], ["리그렛샤", "12154"], ["거대식신", "12056"], ["Pc", "11971"], ["철컹철컹", "11887"], ["바림달", "11878"], ["힛이터", "11604"], ["샤티엘", "11603"], ["에로디", "11142"], ["이성경", "10892"]], "gsm": [["조자룡", "2347616"], ["짖어봐", "2181930"], ["풍월을읊는다", "2000299"], ["에버레트", "1885380"], ["휘셰", "1760648"], ["얼음녹차", "1489255"], ["쏘파인", "1360389"], ["무월", "1284946"], ["나타나라", "1221040"], ["푠푠", "1201248"], ["큐니", "1160462"], ["네잎클로버", "1079700"], ["춘아", "980606"], ["Tsuki'ii", "614934"], ["유데톨", "573154"], ["파트너", "548572"], ["크라이트엘", "543210"], ["윤서리", "500908"], ["엘그니스", "500761"], ["라라아", "500000"], ["새녹", "374970"], ["펭민", "358603"], ["귀욤하늘", "231818"], ["네코미미주세요", "161510"], ["발람", "152870"], ["엘라다", "136725"], ["Coatlique", "134127"], ["누비냐", "115373"], ["밤단밤", "113435"], ["초이''", "92344"], ["화솜", "85792"], ["세림", "76217"], ["늑뭉", "63779"], ["례뉴", "63042"], ["루루애오감쟈주새오", "54392"], ["라헌", "52619"], ["제로'", "51467"], ["Scorpi'o", "50224"], ["이삭몬", "50057"], ["학연", "42520"], ["엘첼", "40373"], ["에킨", "40290"], ["쿠키나무", "40078"], ["와사트", "38441"], ["타임메모리", "37984"], ["페이네스", "34812"], ["으먓", "33414"], ["녹차곰돌이", "30934"], ["키쟌", "29423"], ["반령", "29271"], ["캐이슬린", "26900"], ["Lozen", "26533"], ["파랑블루아오", "25922"], ["초봄봄", "25269"], ["태초의어릿광대거상", "25231"], ["브룬힐더", "22652"], ["천상난희", "21957"], ["레이그란샤", "19920"], ["야미야미냠냠", "19375"], ["구마", "18750"], ["매절", "18501"], ["깜쟈또링", "17932"], ["렝냐", "17437"], ["달보레", "17380"], ["으녑", "17271"], ["에셀로아", "16692"], ["방울꽃", "16159"], ["실루콩", "15680"], ["하이젠", "15637"], ["에이", "15484"], ["솜뮥", "15203"], ["레비안", "15057"], ["에린시", "14522"], ["반하냐", "14070"], ["온시디움", "13548"], ["낙이", "13347"], ["센코", "13188"], ["름달", "12659"], ["마다루", "12346"], ["렴땅", "11652"], ["슈내", "11569"], ["주전자껍데기", "10927"], ["무결", "10619"], ["우주사막", "10597"], ["폰다프", "10222"], ["Shell", "9120"], ["피카츄", "8790"], ["라티그레", "8779"], ["리그렛샤", "7859"], ["투명종이", "7576"], ["퀸트에", "7572"], ["솜슈피", "7182"], ["테움", "6841"], ["에렌", "6750"], ["역린", "6750"], ["비조", "6716"], ["겨울잠", "6324"], ["아탈란테", "6123"], ["인원", "6052"], ["제랑'님", "5870"]], "ltw": [["유예랑", "4000000"], ["사모니안", "2105745"], ["훈장", "1607036"], ["치노", "1593138"], ["Balderich", "1560240"], ["고매님", "1289464"], ["난죠라라펠", "1234567"], ["사이간", "1193168"], ["김사제", "1124518"], ["유'키", "1113531"], ["꿀벌파보스", "967526"], ["갈비''", "962690"], ["은날치", "952705"], ["조와", "945166"], ["망고맛환타", "935266"], ["음률", "900677"], ["무디", "496045"], ["블루우드", "409008"], ["눈물은모르게", "360468"], ["고통과고난", "215310"], ["언호", "166127"], ["타다시", "164780"], ["루셴", "154434"], ["데아", "149773"], ["김전무", "125753"], ["냠냐미풀", "124173"], ["실시아", "117330"], ["감자옹심이", "114774"], ["열심히해본다", "83932"], ["초코바비", "78446"], ["하닌", "66503"], ["안니", "64779"], ["쁘솜", "61495"], ["제갈술사", "51208"], ["정육면체", "51123"], ["반혁", "50440"], ["나티", "50100"], ["헤아르텔", "45199"], ["귤바구니", "42104"], ["미미'", "41299"], ["티바나", "38414"], ["슈플렛", "32527"], ["녹차곰돌이", "30583"], ["녹찻잎", "30522"], ["Vespine", "28920"], ["집에가자진진자라", "25735"], ["독고필태", "25151"], ["라니라니", "25145"], ["디디오", "24187"], ["Cynthia", "22169"], ["주만지", "21551"], ["셔벗", "20980"], ["리오센트", "20524"], ["타쿠", "20294"], ["재은", "19512"], ["로트에이딘", "17812"], ["예후", "17535"], ["빗차", "17250"], ["하론", "16373"], ["너를기다렸어", "16178"], ["레겐", "15411"], ["치킨사주새오", "15090"], ["루오나타르", "14877"], ["모리오", "14279"], ["톰포드", "13521"], ["로딩도와줘", "13221"], ["초봄봄", "13034"], ["녹틸카", "12829"], ["주전자껍데기", "12803"], ["이해랑", "12720"], ["르운", "12702"], ["가류", "11716"], ["플루안", "11340"], ["밀리아리아", "11331"], ["발디프", "11190"], ["치하루쨩", "11153"], ["나나헨", "11113"], ["Ldkey", "10712"], ["춘호", "10581"], ["반율", "10462"], ["팡당", "10427"], ["댕고", "10412"], ["Aquariu's", "10318"], ["미미비", "9165"], ["주예", "8750"], ["미시마에리카", "8163"], ["브룬힐더", "7890"], ["카이르", "7707"], ["티코", "7650"], ["야자", "7549"], ["에이", "7496"], ["동자꽃", "7423"], ["김대일", "7325"], ["누누링", "7273"], ["쫀딕", "7253"], ["워들", "6803"], ["먐뭄", "6400"], ["라봄", "6073"], ["제르빈", "5850"], ["냐메", "5640"]], "wvr": [["아무나힐주지말래요", "2222222"], ["민트베리크런치", "1685122"], ["유덕환", "1675870"], ["루클렌", "1598190"], ["만타인", "1486299"], ["넌이런거하지마라탕", "1380289"], ["초승달", "1304116"], ["제이메린", "1262913"], ["크텐", "1181362"], ["레아나포르테", "1160479"], ["아른", "1141828"], ["미츠히데", "1141060"], ["라인", "1111518"], ["이불잇", "1063210"], ["기다리는마음", "1002515"], ["루룽'", "766619"], ["노논", "711415"], ["람람", "549332"], ["전공", "530516"], ["땨닷쥐", "506029"], ["림사동하이점프", "458913"], ["카르티케야", "426418"], ["유해한에이치", "309114"], ["불투명저스티스", "253011"], ["말랑히모", "155496"], ["현화", "155302"], ["세츠'", "147103"], ["매진", "135884"], ["데니님", "122172"], ["네코야마", "111653"], ["펭민", "106178"], ["태초의어릿광대거상", "103386"], ["히미코", "101654"], ["넌슈가", "100440"], ["오디드", "79945"], ["천언", "71089"], ["레퓨", "70679"], ["데렝", "65974"], ["윤핑", "64816"], ["샘별", "64750"], ["로젠", "62681"], ["게의큰집게", "60287"], ["헤미", "57122"], ["엘스'", "56124"], ["페이네스", "54234"], ["나얌", "53993"], ["요즈미미", "52024"], ["Elroy", "51547"], ["브룬힐더", "50665"], ["미코테회장님", "50009"], ["뭉냥냥", "47016"], ["버터버터링", "42993"], ["까만솜뭉치", "42028"], ["번뇌목사", "41790"], ["부카", "41621"], ["헬다", "35490"], ["녹차곰돌이", "32977"], ["치하루쨩", "32780"], ["코코푱", "30652"], ["결해", "27292"], ["사부이건어때", "25798"], ["교지관", "25369"], ["클로비셰", "24167"], ["므므므", "23430"], ["아이네'", "23262"], ["아르모트", "23144"], ["강이랑", "22673"], ["네모의꿈", "22338"], ["도현'", "22323"], ["영월호", "21748"], ["비사'", "19090"], ["밤샛", "19050"], ["은솜", "18630"], ["부찌", "18582"], ["꾸기잉", "18547"], ["Seol", "18424"], ["공항", "18078"], ["찐악개", "16950"], ["파댱", "16423"], ["마이어스", "16180"], ["이칠홍", "16140"], ["김사비", "15790"], ["반현", "15719"], ["꼬죽사", "14428"], ["사문", "14349"], ["배넌", "14248"], ["타루젠", "12516"], ["한라고라고", "12162"], ["백무", "11842"], ["포포란", "11643"], ["젤라즈니", "11550"], ["헤테르", "11336"], ["체리코테", "10581"], ["인디즈", "10376"], ["B'ibi", "10003"], ["예슬기", "9907"], ["가위와나이프", "9859"], ["다니냥", "9714"], ["와칸다난민", "9629"], ["쌈자", "9601"]], "alc": [["맛미", "2751583"], ["막달레나유트", "1974788"], ["피카츄", "1737375"], ["가디안", "1693423"], ["양효성", "1623567"], ["돕희", "1500000"], ["체리바", "1351751"], ["함수초", "1249212"], ["아리하넬", "1241668"], ["선생밈", "1160047"], ["세베리안", "1070854"], ["유졍", "1024251"], ["춘봉", "926651"], ["Hakulen", "777418"], ["풋풋", "595835"], ["성전태세", "500339"], ["편작", "370148"], ["코쿤", "349482"], ["김베타", "269831"], ["냥자택일떼껄룩", "250921"], ["Onqx", "239982"], ["쏘파인", "236764"], ["초봄봄", "234592"], ["조래도나이트", "232188"], ["Lichas", "197262"], ["하벤", "174184"], ["낯선그림자", "144251"], ["별사탕체", "137442"], ["연수정", "131080"], ["Un'known", "120930"], ["루'펜릴", "116846"], ["테스레미노프", "105664"], ["듀오", "103807"], ["멜로니이", "100424"], ["상한레몬밤", "97979"], ["젤리교주", "83911"], ["개구리의개굴", "76799"], ["라봄", "75806"], ["비조", "74692"], ["흙당근", "70243"], ["물매화", "69204"], ["매지컬룬룬", "62920"], ["달뤼미엘", "56133"], ["별짜", "56123"], ["강광배", "54595"], ["믐달'", "53564"], ["아쿠에리스", "52645"], ["다먕", "50748"], ["오후여담", "50614"], ["말랑히모", "42766"], ["유나의거리", "41952"], ["실비넬", "40196"], ["바닐라푸딩", "39610"], ["뭉먀", "36519"], ["인규", "35999"], ["한열", "35010"], ["나노냥", "34328"], ["하루님", "33805"], ["베라나시스", "32274"], ["녹차곰돌이", "31754"], ["비하늬", "30709"], ["푸기", "30107"], ["샹어", "29315"], ["로모쿠보", "25520"], ["카스티엘로", "25217"], ["곰곰상야캐요", "25200"], ["하게", "25128"], ["카텔라스", "24448"], ["김챱챱", "24321"], ["엘라다", "24037"], ["렴땅", "23418"], ["라이올라", "23250"], ["윤제우", "22310"], ["프레드리", "21475"], ["마영도", "21390"], ["지누콱", "21243"], ["아크렐", "20940"], ["Kyle", "20213"], ["Austerity", "19500"], ["윤헌", "19113"], ["룬메", "18846"], ["달레냥", "17817"], ["Immense", "17670"], ["벅으", "17329"], ["루셴", "16643"], ["엘노아", "16529"], ["다지", "16500"], ["르넬", "15653"], ["데아", "15348"], ["브룬힐더", "15341"], ["히피린", "15297"], ["호떡", "14920"], ["교수", "14847"], ["다미곰", "14760"], ["은여을", "14566"], ["운호", "14190"], ["프늉", "14118"], ["성천룡", "13797"], ["황태자", "13612"], ["화랑운", "13325"]], "cul": [["바네사아", "1919511"], ["서준우", "1800884"], ["타크사카", "1748915"], ["시첼", "1571049"], ["모마모토", "1339568"], ["으르", "1257285"], ["매지컬룬룬", "1170046"], ["독제", "1156682"], ["목화솜", "1150605"], ["키마", "1136131"], ["온게", "1124948"], ["땅꼬마난쟁이", "931890"], ["묘운", "904584"], ["Ranelika", "850657"], ["아이솔솔", "616500"], ["Kyle", "516630"], ["에오미테", "504955"], ["하게", "464652"], ["유골", "444400"], ["나쯔나", "417301"], ["의욕'", "391444"], ["리리카", "372418"], ["치소", "310230"], ["Dareia", "297598"], ["쏜늉", "277057"], ["누누이", "201790"], ["기영원", "174100"], ["신월설희", "172302"], ["별상어", "171216"], ["학도", "143844"], ["알리섬", "141606"], ["차가", "137436"], ["에탈", "132407"], ["넛넛베베", "119025"], ["야옹이아니야늑대야", "103613"], ["리나세", "100146"], ["운해", "84161"], ["에피알티스", "83887"], ["슈니엘", "82913"], ["방시혁", "80194"], ["셀케트", "79716"], ["덥냥", "79075"], ["단예", "78580"], ["몽상가", "75640"], ["Primular", "73868"], ["말랑히모", "69587"], ["히카에데", "65075"], ["천애화", "62455"], ["티카람", "60912"], ["챠오'", "60591"], ["코라이", "54875"], ["루오나타르", "53652"], ["제노랄드", "53341"], ["아말다", "52294"], ["할드라스", "51057"], ["지평선", "49346"], ["알라미고길동", "48020"], ["뚜뚜뚜뚜뚜뚜뚜뚜뚜", "44649"], ["Castiel", "41765"], ["에스텔라나디아", "40040"], ["에젠마", "36504"], ["구본하", "33699"], ["프리세이르", "32208"], ["유한호", "31375"], ["치즈태비고양이", "30694"], ["녹차곰돌이", "29519"], ["요리왕", "29308"], ["유키린'", "28737"], ["세피냥", "28082"], ["포포푸", "27807"], ["백설설탕", "27246"], ["울다하풍의'모험가", "26656"], ["타다시", "25407"], ["새살이솔솔", "25230"], ["도멈머", "24886"], ["태헌", "23935"], ["Vespine", "22986"], ["브룬힐더", "22597"], ["슈마일리", "22351"], ["삼월의토끼", "21749"], ["괭하령", "20476"], ["리오센트", "20069"], ["리세잔", "19195"], ["메사라", "17870"], ["마키엘라", "15816"], ["화빈", "14700"], ["랑먕묭", "14358"], ["동자꽃", "12681"], ["시계", "12610"], ["릿챠", "12433"], ["엘리안", "12218"], ["김사제", "12120"], ["동동", "12113"], ["타테샤", "11901"], ["주양''", "11667"], ["카율", "11588"], ["흑군", "11188"], ["형서", "11034"], ["유황", "10595"], ["아따비키랑께", "10343"]]}, "chocobo": {"min": [["배숙희", "1000000"], ["템퍼런스", "888880"], ["연두루미", "882407"], ["핸드폰", "870364"], ["헤디아", "870357"], ["류삭", "868337"], ["꿀향", "833137"], ["그루넬", "828397"], ["와니야", "826901"], ["티발트", "815820"], ["얘가힐서줄거야", "796001"], ["가옌", "787541"], ["라쿠룬", "777307"], ["퓸퓸", "748695"], ["카루바스", "735877"], ["송미소", "731695"], ["Kuo", "725817"], ["후추'", "541608"], ["Feuermann", "500637"], ["플로", "500000"], ["백측", "443174"], ["카에데", "440000"], ["소노랑", "396396"], ["고장난눈물샘", "348362"], ["Jura", "345350"], ["나오냥", "260745"], ["이즈미'이오리", "250741"], ["엘리움", "250000"], ["산봄", "239647"], ["쿠로'", "238382"], ["으앙죽음", "222026"], ["파써낙스", "204009"], ["야아토", "188249"], ["김금훤", "182743"], ["Zaiha", "170104"], ["냥핑이", "162663"], ["라일", "158935"], ["하달", "156226"], ["남파람", "155624"], ["모엘리", "155564"], ["랑팅", "153677"], ["실리안", "142339"], ["아쌈밀크티", "135826"], ["지위", "135126"], ["조부", "132717"], ["배고플나이", "130727"], ["Atypiacl", "129209"], ["히마리'", "127197"], ["형원", "124553"], ["멜론골뱅이", "124540"], ["제르니스토", "116222"], ["꾸픈", "114985"], ["Journey", "113118"], ["토끼유", "112153"], ["가나", "109832"], ["프롤레타리아", "105411"], ["서율아", "105355"], ["룽네", "102868"], ["박카스노맛", "101741"], ["Yana", "101399"], ["에프아", "101121"], ["Chevalier", "100765"], ["마요메즈", "100406"], ["쟈크스", "100398"], ["아마루스", "96983"], ["인혜", "95328"], ["크로젠", "95036"], ["뮤런'", "94698"], ["닌닝", "93848"], ["룬빈", "93388"], ["씽호", "89541"], ["오딘", "88424"], ["쟇겨", "88373"], ["파린이", "88027"], ["와슈", "87518"], ["쿠샤", "87127"], ["젤리삐", "86131"], ["라임세레니티", "85954"], ["펜하나", "83592"], ["믿음소망사랑니", "81925"], ["유료로해주는힐러", "81820"], ["꼬카", "79071"], ["송개", "78782"], ["답이", "78412"], ["이하티", "77714"], ["스게", "76996"], ["전애인", "76432"], ["집나간니학점", "75138"], ["하려한", "73835"], ["의하여", "73701"], ["요러고", "72916"], ["츄르츄르", "70028"], ["로단", "68662"], ["유에르텔", "67775"], ["페페라", "67622"], ["구연산비타오백", "66088"], ["연어초밥", "64224"], ["라트렌", "63338"], ["김만득", "63041"], ["호냔", "60745"]], "btn": [["츄하이모모", "987654"], ["시니컬로빈", "961849"], ["메로코미", "903842"], ["Brise", "896886"], ["탈리에신", "888888"], ["빌라넬", "862717"], ["버간밥", "815280"], ["Desktop", "758045"], ["레딕", "709223"], ["목마른철새", "672881"], ["알타리무칠천오백원", "653577"], ["글라시스", "636924"], ["리샨'티아", "616370"], ["언묘", "602876"], ["해씨", "500057"], ["해피너츠", "394836"], ["바람의수호자", "356620"], ["쟈허토르테", "338450"], ["테루타르소스", "307633"], ["이우진", "292375"], ["김편탁", "289245"], ["견오", "289059"], ["결연", "272119"], ["시칼리", "249012"], ["르꾸'", "243216"], ["르헤", "229627"], ["Tod", "227040"], ["삼나무", "214820"], ["Atypiacl", "213640"], ["청포도그린티", "211519"], ["단하시", "207588"], ["허시완", "183902"], ["방배동고라니", "183297"], ["Journey", "176515"], ["Moos", "173995"], ["송미소", "166593"], ["Nectan", "160265"], ["레오니카", "153806"], ["야다비켜", "153591"], ["강우'", "151546"], ["슬긔", "137130"], ["탱그링", "134725"], ["알타이", "134499"], ["또담", "132926"], ["괍콘", "128915"], ["꽃가지", "127890"], ["표류", "123810"], ["난고래", "123456"], ["랫사팬더", "123357"], ["아이돌디펜스", "123286"], ["왕소야", "121199"], ["비간", "110819"], ["랑시시", "108560"], ["리리샤", "105902"], ["정이구현", "105103"], ["결애", "104316"], ["슈반'", "103960"], ["Morfhis", "103949"], ["호화", "102935"], ["페페라", "102783"], ["아비오르", "99058"], ["펭랑", "95838"], ["혼이나감", "95372"], ["아크살다르", "94378"], ["Beeeeeee", "92853"], ["Riroy", "91583"], ["환애", "90888"], ["힐줄게", "89227"], ["카횩", "88368"], ["카밀'", "87805"], ["쿠헬늘보", "87053"], ["페나디르", "86985"], ["슈슈몽", "84152"], ["검현", "82526"], ["정눈꽃", "81555"], ["나를위한", "81170"], ["Ray", "79631"], ["옌붕이", "78276"], ["오감자", "77934"], ["프테라곤", "76850"], ["크로젠", "76504"], ["리다인", "75726"], ["연어초밥", "72114"], ["일평", "70849"], ["루키님", "69115"], ["려휘", "68799"], ["김삼칠", "66933"], ["지위", "66891"], ["달에가려진별", "64813"], ["냥핑이", "64461"], ["아모르다쿠뽀", "63783"], ["형원", "63738"], ["완두콩'두콩", "61981"], ["유도라", "60675"], ["리베르테스", "59475"], ["오리나", "59475"], ["냐쥬", "58729"], ["제스트", "58509"], ["달호수", "57893"], ["은밀한모략가", "57785"]], "fsh": [["답변", "3115466"], ["가장오래된꿈", "3099750"], ["연출", "2729272"], ["알팔파", "2641664"], ["시오네", "2553719"], ["모르엣", "2537309"], ["아니왜그걸", "2484105"], ["루달", "2435731"], ["멸살악개", "2435491"], ["스모모", "2212773"], ["예쓰", "2146891"], ["센린", "1943772"], ["오르타빈", "1835074"], ["히나이치고", "1822988"], ["즈엥", "1745186"], ["유코브", "1591832"], ["세루핀", "1183129"], ["양심리스", "1144310"], ["써르", "1040315"], ["하라쇼", "735212"], ["베리타세룸", "734007"], ["웨어", "727536"], ["Xis", "675101"], ["니르기", "654511"], ["알프트라움", "637029"], ["고구마치즈돈가스", "609582"], ["에뮤사", "543210"], ["형그사람누구에요", "536710"], ["호화", "515877"], ["묵은지쥐치찌개", "506702"], ["느르흐", "486391"], ["픂픂", "480769"], ["더엉", "480000"], ["Mkorange", "438439"], ["멩고", "415298"], ["카미씨", "414057"], ["록단", "412663"], ["Ice", "407091"], ["아가테'", "356645"], ["물개쟝", "328595"], ["리리아라", "328330"], ["왕의길에진입합니다", "310742"], ["앙구스", "309303"], ["퍼로", "306667"], ["앤버리움", "304201"], ["두부'", "295797"], ["푸링링", "287790"], ["Doublep", "284671"], ["헬로해피월드", "264850"], ["서세린", "248514"], ["시오이리노", "241088"], ["민트초코케이크", "239871"], ["불곡산차돌박이", "239470"], ["먹보", "237442"], ["띠모", "232768"], ["오르도", "202527"], ["루유", "192822"], ["영찬", "191055"], ["Orel", "184863"], ["잭네이피어", "179152"], ["하넬라", "174852"], ["사앙", "173530"], ["시냇", "173493"], ["리갈루", "166727"], ["마유윳치", "165305"], ["그랜드햄스터", "164888"], ["단영", "160344"], ["아클리스", "160207"], ["피격", "159403"], ["꿀곤듀", "154867"], ["무등산세발낙지", "151469"], ["연어초밥", "149147"], ["지존공허몬스터", "145039"], ["소우", "143716"], ["포도킹", "141259"], ["Dichlicht", "139866"], ["애스티니앙", "131942"], ["꼿게", "129464"], ["운명의실", "128077"], ["호타타", "124874"], ["독식자", "123278"], ["주스'", "112809"], ["꼬맹꼬맹", "108366"], ["Celrenea", "107629"], ["케이메이'", "106759"], ["정윤우", "103301"], ["달비부위", "102473"], ["북극곰덩어리", "100615"], ["로체", "99775"], ["정하랑", "98974"], ["Damioh", "94382"], ["Reim", "94238"], ["김라치", "94170"], ["매류", "92727"], ["테거스켄", "92548"], ["Mangpha", "90019"], ["악현", "88695"], ["무류", "86042"], ["자퇴", "85494"], ["사프란", "83415"]], "crp": [["하얀마법사", "2981305"], ["폴리덴트", "2806659"], ["Bahn", "2150000"], ["도키", "1517178"], ["Pandorah", "1238625"], ["테테리테리", "1202232"], ["카오르", "1170930"], ["류호랑", "1072497"], ["휘감하랑", "940070"], ["트라크", "897769"], ["때리지말아주세요", "712129"], ["나니란", "678245"], ["아냐스타샤", "638076"], ["이보리체", "630110"], ["달에가려진별", "495726"], ["김진석", "473253"], ["베이컨교수", "302829"], ["핑핑핑", "294071"], ["이이선", "266158"], ["Erinn", "250586"], ["부스러기", "223185"], ["참새", "173076"], ["너만의동생", "163941"], ["머랭라떼", "160874"], ["냐쥬", "158903"], ["람란우", "142769"], ["김코르", "115140"], ["강력반최문성", "106800"], ["청시", "104969"], ["큰인간", "84702"], ["주테", "77930"], ["하나에", "75617"], ["포차리", "74083"], ["강우'", "73711"], ["제스트", "66729"], ["Ardbert's", "65665"], ["재능선생", "57386"], ["설국의", "53315"], ["자와자와", "51408"], ["갖고싶다'낚시신", "50712"], ["걀달", "50330"], ["슈크림빵하루", "48209"], ["Potatoy", "45734"], ["연어초밥", "45348"], ["양무영", "43866"], ["리리샤", "40101"], ["시헌", "40100"], ["페페라", "36319"], ["카얀", "35760"], ["이단'카르츠", "31537"], ["해청", "30082"], ["슈슈몽", "29797"], ["베라딘", "27198"], ["찹쌀멜론", "23542"], ["사령관", "23465"], ["블래빗", "23445"], ["유도라", "23310"], ["원초", "23175"], ["이스타", "22859"], ["크레우스", "22604"], ["전촹촹", "22030"], ["Worry", "21280"], ["미나비야", "20307"], ["벤군", "20249"], ["아비오르", "20066"], ["Riteo", "19748"], ["세이사", "18487"], ["Cindy", "18098"], ["옥수수빵", "17839"], ["밀키화이트", "17649"], ["칸델라", "16391"], ["염호", "16200"], ["오비오비", "15730"], ["설표'", "15492"], ["노을품", "15383"], ["모시땅", "14856"], ["일찬", "14615"], ["모르포", "13525"], ["르헤", "12921"], ["김규식", "11940"], ["파쇄의게리크", "11733"], ["카즈마나", "11613"], ["Prey", "11565"], ["명랑한방랑자", "11289"], ["꽃옌", "10860"], ["추상우", "10858"], ["비간", "10342"], ["마음빵", "10040"], ["헝겆", "9781"], ["별상어", "9733"], ["레이블랑", "9316"], ["펭랑", "9125"], ["무기력자", "8961"], ["달이''", "8947"], ["이카", "8838"], ["낭량", "8791"], ["도르테시아", "8681"], ["아렌델", "8508"], ["젠제님네키리", "8455"], ["Lunaire", "8406"]], "bsm": [["남궁선아", "3014658"], ["엑쎌린", "2645386"], ["꼬견", "1680727"], ["허니듀크", "1352402"], ["레드벨", "1228706"], ["은재이", "1140919"], ["고토부키레이지", "1111917"], ["티란", "1100007"], ["이저녁", "1051761"], ["엄마", "1047331"], ["메리", "1001328"], ["데장님", "999172"], ["살로메", "992112"], ["루케트", "967403"], ["무기한보류중", "754776"], ["Qirtm", "501273"], ["재규", "490409"], ["열민", "470822"], ["수달찌", "459379"], ["Schmitt", "333139"], ["바닥", "321851"], ["어둠의전사", "317214"], ["체리'''", "283358"], ["타이난", "221992"], ["아루카스", "154876"], ["접지동물", "150100"], ["끼리", "147763"], ["자양화", "147584"], ["프릴", "123076"], ["살미아키", "99951"], ["렝또", "95679"], ["Shogle", "94486"], ["이크리트", "93998"], ["유베르", "87780"], ["에리카", "70509"], ["나이팅쿠뽀", "67980"], ["Lesser", "67595"], ["윤반령", "66436"], ["춘덕", "64142"], ["카나'페", "64026"], ["시로이누", "58458"], ["에뮤사", "57279"], ["사랑해요레옹", "57178"], ["넌틀렸어난간다", "55990"], ["호타타", "55740"], ["바이올라", "53450"], ["레스타드", "51219"], ["Hikari", "50579"], ["수평", "47897"], ["뉴비상님", "43479"], ["아탈리브", "41289"], ["거니거니", "36767"], ["쭈케", "34762"], ["하르바르티", "30868"], ["참외롭다참외로워", "30585"], ["Sol'", "29524"], ["유월의별", "27594"], ["레이디아터", "25185"], ["페페라", "24878"], ["초록이조아요", "23725"], ["청연월", "23641"], ["티파록하트", "23192"], ["원초", "21663"], ["픂픂", "21630"], ["재연", "21506"], ["Le'a", "19816"], ["미파", "19455"], ["키도야", "19320"], ["어글가지", "18819"], ["임셜리", "18101"], ["Prey", "15009"], ["연어초밥", "14785"], ["백문후", "13810"], ["카라아게", "13366"], ["펜로즈", "13334"], ["모냑", "12062"], ["찬휘", "11848"], ["흑연'", "11539"], ["자와자와", "11361"], ["타루'타루", "11264"], ["Hastilia", "11046"], ["이설묵화", "9776"], ["개념탈주", "8993"], ["태범'", "8729"], ["사랑해", "8353"], ["나이스체리", "8222"], ["제랄드티아", "7980"], ["Guylian", "7940"], ["최배려", "7381"], ["닭의수호신", "7322"], ["Lunaire", "7311"], ["라이프이즈포테이토", "7157"], ["옆집노예", "7155"], ["한담", "7012"], ["모략", "6690"], ["대수", "6658"], ["타나페리", "6654"], ["모나", "6426"], ["이즐펠", "6322"], ["Ruank", "6289"]], "arm": [["아리니에타", "2437877"], ["파트너", "1908196"], ["재찬'", "1888351"], ["피잇", "1870105"], ["운결", "1555484"], ["아마루스", "1502958"], ["람룡", "1475104"], ["피나레나", "1469181"], ["으스으", "1432517"], ["블러드트레일", "1429144"], ["호랭호련", "1362284"], ["김꾹", "1300540"], ["하나", "1299067"], ["멮창이", "1169137"], ["머글루", "1023687"], ["라랴토", "809770"], ["온돌유", "717837"], ["아리얀", "588098"], ["멜리나", "580316"], ["헤븐투헬", "578645"], ["연누리", "566816"], ["첨예한", "343588"], ["페틸렌", "335858"], ["박카스노맛", "206429"], ["단영", "201297"], ["O'bell", "201011"], ["유료로해주는힐러", "188976"], ["허니마렌", "184223"], ["시나위", "181160"], ["에플리첸", "178814"], ["참외롭다참외로워", "119438"], ["렐라아", "107575"], ["Ardyn", "106040"], ["얘가탱서줄거야", "95962"], ["행복한종말", "95352"], ["롱차", "87165"], ["Damage", "83961"], ["토르테", "67702"], ["카스텐", "61737"], ["배동", "55454"], ["리트'리버", "55095"], ["궁합위계", "52187"], ["아슈린", "51465"], ["하얀밤", "51377"], ["호냔", "50484"], ["페페라", "48891"], ["태여", "42449"], ["연제", "40158"], ["Daphne", "39632"], ["Le'a", "39093"], ["Ceslea", "38580"], ["룽네", "37644"], ["타이맥스", "37502"], ["아랫마을고양이", "37449"], ["세류룩", "36649"], ["보건소", "36090"], ["이하티", "35810"], ["이숲", "34694"], ["승천", "34693"], ["츠유", "33180"], ["Zaiha", "32061"], ["이중혁", "30706"], ["담하", "29734"], ["두디디딩", "27710"], ["레이븐", "26847"], ["반시", "26389"], ["하론", "26340"], ["라공", "26031"], ["롤스브랜드", "23921"], ["에흐토야", "22860"], ["훈징", "22797"], ["엔느", "22063"], ["얘가힐서줄거야", "21905"], ["원초", "21846"], ["쁘뇽", "21439"], ["현택", "20678"], ["노이르", "20362"], ["차사", "19760"], ["연어초밥", "19640"], ["휴닝카이", "18934"], ["리베로", "18523"], ["서솜비", "18517"], ["케이단", "18023"], ["Orel", "17324"], ["아를렌", "14918"], ["범율", "14384"], ["냠냠냠냠냠", "14049"], ["린토토", "13081"], ["나이스체리", "13066"], ["에뽀", "12300"], ["Michell", "12210"], ["시누", "12144"], ["Guylian", "11970"], ["김용구", "11827"], ["초야", "11400"], ["햄코", "10938"], ["티타니아명수", "10112"], ["다니안", "10050"], ["자와자와", "9730"], ["류삭", "9680"]], "gsm": [["르미에라", "3427973"], ["낙두", "2222222"], ["애슐리", "1852517"], ["난다난다니얀다", "1822052"], ["현이곰", "1750000"], ["Acky", "1675266"], ["Meilleure", "1660142"], ["유카리오트", "1454988"], ["라쿠시", "1205945"], ["절명", "1119537"], ["라하사", "1070621"], ["하프트", "944935"], ["지적", "714715"], ["나비잔", "551156"], ["의령", "486093"], ["이즐펠", "407318"], ["쿠도신이치", "319677"], ["라비올", "307521"], ["라비엔토", "303514"], ["Kugu", "267493"], ["Katrine", "250237"], ["리리룬", "210970"], ["챠라리", "193612"], ["루싱", "182671"], ["키실", "153476"], ["사프란", "134735"], ["진우웅", "132813"], ["라트로반", "132611"], ["로단", "129054"], ["유교", "124631"], ["레티씨", "112688"], ["말차모나카", "111249"], ["Lazuli", "96628"], ["휼이", "92915"], ["백문후", "87720"], ["래담", "86398"], ["슈에", "81927"], ["박뽀삐", "79089"], ["안예담", "77574"], ["진홍", "71112"], ["하넬라", "70224"], ["크로젠", "66639"], ["Nuve", "61981"], ["미야옹", "57681"], ["별하임", "57097"], ["아이워르", "57068"], ["뮤런'", "55585"], ["블라세", "55441"], ["소위", "53605"], ["죠'", "50097"], ["훼손", "47293"], ["유라한", "41996"], ["그랜드햄스터", "40433"], ["리하모", "37396"], ["네스라", "33692"], ["초코하몽", "33361"], ["히나구미", "31759"], ["왼팔의흙염소", "30030"], ["별메가안했어요", "29071"], ["근청", "28345"], ["페페라", "27780"], ["아티랑스", "24633"], ["연어초밥", "24484"], ["교하", "23631"], ["라하베르", "23566"], ["아즈벤", "23490"], ["없는별", "23142"], ["테르무네", "22555"], ["원초", "20395"], ["리리치카", "20377"], ["마음빵", "18179"], ["Aila", "18017"], ["에리카", "16667"], ["천수국", "16240"], ["Sain", "15194"], ["김사비", "14601"], ["용'기사", "14520"], ["세범", "14450"], ["치엘라", "14279"], ["몬드", "13710"], ["아이로넨", "13151"], ["단팥찌", "13073"], ["야쿠쟈", "12125"], ["스케", "11761"], ["실격", "11527"], ["황금올리브치킨", "10174"], ["한담", "9780"], ["언이", "9510"], ["세이레인", "9473"], ["힐러사제", "8358"], ["몽몽실", "8280"], ["율언", "8172"], ["김재교", "7718"], ["임나", "7460"], ["노을품", "7410"], ["앰버서더", "7359"], ["프리스릭'", "7200"], ["샤미파르팡", "7167"], ["호시노히카리", "7020"], ["서야'", "6896"]], "ltw": [["아린시엘", "2500000"], ["Guylian", "2206483"], ["라비엔토", "1720959"], ["근찬", "1153916"], ["알약", "1112842"], ["어글이뭔가요", "1100162"], ["가나", "1077395"], ["절알렉과몰입솜냥이", "1033205"], ["정인랑", "989884"], ["닭의수호신", "906176"], ["콩이", "817219"], ["호빰", "776832"], ["알헤이나", "770836"], ["백수국", "759164"], ["투리구슬", "740703"], ["세균", "591659"], ["혼이나감", "501178"], ["캐빈디쉬하비", "435459"], ["령하월", "401986"], ["Zeva", "397803"], ["라노시아젤리", "313657"], ["가지가지", "285062"], ["리베르테스", "231125"], ["키어로", "180049"], ["루카락시아", "178012"], ["Ethan'", "173931"], ["노이라", "160453"], ["카티에르", "148196"], ["서야'", "142655"], ["랴라", "135177"], ["타타끼", "120992"], ["유리구슬", "109634"], ["홍온", "105030"], ["되다만몽", "91615"], ["에다흐", "85949"], ["샤인류아인", "85033"], ["용혈끊기면던짐", "73241"], ["한나나", "63655"], ["완두콩'두콩", "60396"], ["쟈근부리또", "56055"], ["잔별'", "55983"], ["김하루", "54012"], ["데이", "53081"], ["요슛", "51118"], ["쟈근새쌱", "43547"], ["유키아", "41816"], ["제르모니아", "38455"], ["페페라", "35751"], ["에레노이안", "31148"], ["독고정만", "30920"], ["알타이", "30680"], ["페세", "30302"], ["방사능상어", "30277"], ["에루아", "30073"], ["별빛매듭", "30055"], ["연어초밥", "29135"], ["펜잘큐", "27185"], ["경각", "24941"], ["파디", "24075"], ["원초", "20571"], ["그랜드햄스터", "19705"], ["소니투스", "18323"], ["온일", "18124"], ["Onyx", "18120"], ["메르헨나인", "16110"], ["무결'", "15990"], ["쟌테", "15856"], ["오비엔", "15793"], ["한다비", "14992"], ["나이스체리", "14823"], ["갈리스피", "14801"], ["풉크", "14197"], ["무기력자", "13489"], ["베리요거트", "13295"], ["다메요", "13212"], ["오츠카", "13161"], ["바람과함께사라지다", "12865"], ["마두철", "12549"], ["율무무", "12510"], ["펜하렐", "12450"], ["보나넴", "11954"], ["언이", "11670"], ["샤드르", "11400"], ["마유윳치", "11284"], ["치엘라", "11030"], ["강우'", "10791"], ["유라랑", "10786"], ["체리'''", "10232"], ["허니아이린", "10170"], ["검현", "9917"], ["사랑해요레옹", "9787"], ["눈보라곰", "9400"], ["공조판서'", "9239"], ["라야닉", "8800"], ["옥수수빵", "8599"], ["뮬레이", "7934"], ["먹보", "7915"], ["히비케", "7869"], ["노말회원", "7792"], ["체르비", "7620"]], "wvr": [["Haqua", "2888887"], ["리피슈", "2687589"], ["은슈슈", "1722706"], ["계연", "1702667"], ["코쟁이야", "1253156"], ["힐스", "1020966"], ["란화", "978809"], ["시목", "922548"], ["Jelly", "873044"], ["루뽀", "862914"], ["콘크리트", "826558"], ["엘사", "620467"], ["전애인", "576022"], ["하코자키세리카", "356220"], ["로슈", "337141"], ["제프만", "290771"], ["두부쿵야", "192115"], ["미온'", "170288"], ["쿠웨일", "166869"], ["아도라", "163825"], ["려휘", "155863"], ["엘미나", "155821"], ["세이프리드", "138184"], ["에레노이안", "123631"], ["봄여름", "110306"], ["치엘라", "103022"], ["솅종엉졩", "101910"], ["밍슈", "101397"], ["슈반'", "100086"], ["텡귄", "66009"], ["쫑개", "61427"], ["나이스체리", "60810"], ["카헤", "53885"], ["양되다만것", "52760"], ["딸기맛환타", "52151"], ["오즈냐앙", "51627"], ["율한", "50760"], ["씨시아", "50222"], ["유클레이스", "50098"], ["별빛조각", "45707"], ["서준", "45306"], ["꽃옌", "45253"], ["르딘", "45080"], ["민무늬", "45051"], ["박도월", "43361"], ["안젤티온", "39899"], ["메이버릭", "39711"], ["령월하", "39683"], ["로즈블러썸", "35657"], ["꼬마친구프레이", "35321"], ["퓨라쥬", "34750"], ["젤코바", "34714"], ["달호수", "34562"], ["샤치", "31462"], ["원초", "29504"], ["다이델", "27595"], ["루비스티네", "27356"], ["페페라", "26977"], ["무결'", "26070"], ["Haleines", "24920"], ["그라하티아", "23125"], ["유라테이", "22905"], ["선지국", "22419"], ["블러핑", "21948"], ["살의", "21555"], ["랑시시", "20812"], ["유월의별", "20524"], ["기니", "20146"], ["아느네", "20120"], ["방가어", "19998"], ["용기삽니다", "19441"], ["허태유", "19366"], ["Fel", "18725"], ["연어초밥", "18198"], ["Sie", "16027"], ["차사", "15041"], ["유피포", "15000"], ["록녹", "14923"], ["Sain", "14731"], ["다샨", "14656"], ["왈버", "14622"], ["엘블라우", "13650"], ["숙쭈", "13618"], ["수을", "13380"], ["Xuoqef", "13113"], ["헝겆", "13000"], ["난다난다니얀다", "12461"], ["채율", "12393"], ["Zynys", "12288"], ["아가슈", "11987"], ["라스티카", "11733"], ["세처", "11726"], ["인생게임중", "11587"], ["호르티", "11445"], ["마그리에", "11394"], ["떡볶이소스", "11160"], ["서야'", "10854"], ["알파님", "10814"], ["엘루마", "10710"], ["헤얀달", "10639"]], "alc": [["부란다", "4567890"], ["탈모제", "2452549"], ["루도비쿠스", "2096627"], ["바삭팽긴", "1851391"], ["류혜윰", "1542166"], ["시포웰", "1501155"], ["Novem", "1362930"], ["사르르", "1360097"], ["겸애", "1353649"], ["하은설", "1328026"], ["파르페", "1308136"], ["바이에리", "1300018"], ["치즈키쉬", "1012049"], ["Une", "684569"], ["살육의제노사이드", "535888"], ["솜니아토르", "529244"], ["라젤", "504536"], ["Moothie", "504122"], ["Mika", "502185"], ["공대에서기믹틀린놈", "383201"], ["호젤", "343965"], ["팬더''", "231814"], ["김크롱", "205201"], ["에티어", "203283"], ["엠비", "186922"], ["카가나비", "168459"], ["이니그마", "157817"], ["Mune", "151388"], ["련아", "131665"], ["Le'a", "127732"], ["도담'", "116340"], ["상하준", "116246"], ["칼트만", "116137"], ["외로운주먹", "86276"], ["고대", "83166"], ["홍염", "82627"], ["에너미컨트롤러", "81376"], ["잔치", "75210"], ["Skuld", "73759"], ["냥고", "73005"], ["라노시아젤리", "65142"], ["개념탈주", "62488"], ["감율", "59787"], ["야타이밍", "59129"], ["닌닝", "54616"], ["첩자소드", "54217"], ["김삼칠", "51444"], ["공주의집사보라상", "50130"], ["픂픂", "50070"], ["Damioh", "47402"], ["원초", "45717"], ["병아리콩콩", "45689"], ["츠유", "43440"], ["초록옷젤다", "42676"], ["키실", "40724"], ["정인랑", "40700"], ["키아르", "38594"], ["티라챠", "38514"], ["이루", "37817"], ["Kailey", "36813"], ["용남", "35787"], ["연어초밥", "35367"], ["무림만두", "35010"], ["별닮", "33512"], ["가르파초", "32817"], ["론도르", "31766"], ["세베카", "30712"], ["빙뿅", "30581"], ["페페라", "27844"], ["Mercy", "27330"], ["슈가하", "26772"], ["앙나", "26583"], ["찌링", "26339"], ["혜릴", "26196"], ["눈보라곰", "25591"], ["교선", "25322"], ["박하은", "23916"], ["댕이", "22986"], ["토토로", "22200"], ["표범'", "22021"], ["미르썬", "21117"], ["파나미르", "20812"], ["유메링", "20753"], ["불곡산차돌박이", "20536"], ["Schmitt", "20319"], ["율하", "20099"], ["Haeso", "19772"], ["Atypiacl", "19350"], ["이즐펠", "19298"], ["가르릉", "18871"], ["나이팅쿠뽀", "18598"], ["자브에'티아", "18372"], ["테이아'", "17294"], ["Journey", "17280"], ["돌핀씨", "17093"], ["김장여제김정은", "16691"], ["청도", "16688"], ["함소영", "16020"], ["북극곰덩어리", "15762"], ["Endellion", "15415"]], "cul": [["면세된말랑카우", "2004736"], ["펨프", "1621101"], ["디미르", "1400000"], ["으앙죽음", "1400000"], ["동백", "1300166"], ["칼트만", "1171701"], ["니람", "1128679"], ["답이", "1122544"], ["율마", "1116287"], ["Moothie", "1060168"], ["프릴", "1051135"], ["펜다이크", "1025942"], ["콘치즈고로케", "1010471"], ["헬리아", "987790"], ["자몽하다", "925596"], ["에르카델", "904936"], ["눈보라곰", "893916"], ["무기력자", "862914"], ["벤야민하스", "740962"], ["체리코'크", "392711"], ["Chevalier", "374094"], ["참새", "359014"], ["루카엘라", "350989"], ["설낭만", "340614"], ["김코르", "327237"], ["연어초밥", "297383"], ["도담도담", "266278"], ["힌둥힌둥", "226996"], ["김사비", "225483"], ["아리루", "208472"], ["맆드", "200121"], ["김삼칠", "184570"], ["캔디사랑꾼", "174502"], ["카맥스", "171625"], ["Baiqi", "163072"], ["Lyene", "151215"], ["미니텐더", "141869"], ["Clark", "124581"], ["키숀", "110057"], ["엄춘식", "95437"], ["오레오딸기크림", "94009"], ["Rego", "86407"], ["메리울프", "80500"], ["견우", "78801"], ["히다토스", "70724"], ["Hankua", "68566"], ["호디", "66485"], ["소니투스", "65224"], ["하늘말랭이", "61539"], ["카가나비", "59433"], ["밤혜씨", "57313"], ["모냑", "53971"], ["사기고양이책", "51760"], ["아그나르", "50976"], ["망고셀러드", "50748"], ["홍류", "50364"], ["효빕", "46922"], ["케이메이'", "46061"], ["페페라", "43649"], ["설야", "41609"], ["키리티", "40766"], ["프랄린", "38466"], ["수라라", "38256"], ["킴플", "36469"], ["원초", "35764"], ["루나프레야", "34924"], ["퍼로", "34603"], ["지위", "33660"], ["아히발트", "33608"], ["키르시얀", "32458"], ["에레노이안", "30183"], ["후페", "30016"], ["블러핑", "28460"], ["제제란", "27782"], ["혁''", "27295"], ["에르미온", "26784"], ["호화", "26050"], ["라도반", "23993"], ["이서아", "23789"], ["Aim", "22634"], ["꽃의마술사멀린", "21714"], ["Sempre", "21366"], ["카밍", "20887"], ["빵재", "19847"], ["냥핑이", "19682"], ["쟈크스", "19611"], ["니콜라이", "19463"], ["에프아", "19341"], ["큐르", "19334"], ["C'amellia", "19162"], ["위리데로르", "18669"], ["치엘라", "18449"], ["캐빈디쉬하비", "18128"], ["토마스통신기", "17210"], ["N'agi", "16080"], ["최미호", "15650"], ["난고래", "15226"], ["나래'", "14847"], ["윤설하", "14693"], ["리리아라", "14297"]]}, "carbuncle": {"min": [["바이츠", "1020256"], ["암다", "1000038"], ["멜다니아", "952030"], ["마콩", "932251"], ["엔라하즈", "931060"], ["윤화령", "914007"], ["엘디아", "885377"], ["비시아", "873629"], ["스키쇼", "872632"], ["조금전그인간", "871601"], ["베레자반트", "866280"], ["호양", "841915"], ["Ssmaa", "819004"], ["Haerin", "814004"], ["수제자", "804269"], ["백록'", "792314"], ["모르피스", "705711"], ["델리비", "590641"], ["저아닌데요", "522699"], ["덕구", "500000"], ["Monas", "418912"], ["유넬", "405782"], ["엘하난", "390055"], ["리리엘", "370992"], ["페이얀", "349172"], ["루시티아", "340691"], ["수걍", "336137"], ["니츠케", "322814"], ["강개", "297147"], ["아이지아", "278840"], ["고양이빵", "258071"], ["쇼넨베르트", "252727"], ["시하르", "252290"], ["받건희", "244218"], ["레모니", "236061"], ["웨딩벨", "223953"], ["다피르", "222222"], ["갸릉", "221771"], ["솔예담", "203250"], ["웬시", "200020"], ["체리블라썸", "195529"], ["피니카", "192201"], ["밍밍잉", "190427"], ["아발락", "184889"], ["샌팻", "183654"], ["전설의용사님", "182339"], ["프로세", "177897"], ["슬빡이", "177774"], ["섬다", "175264"], ["온우주", "163390"], ["핑꾸감쟈", "159582"], ["직선", "158948"], ["톤톤", "155417"], ["스니레", "152292"], ["섭목이", "146550"], ["휘얀", "144555"], ["Mandarin", "140255"], ["Brilliant", "136968"], ["마리닐", "135677"], ["핫세", "135376"], ["메메타아", "135295"], ["라야라", "133599"], ["제련", "132974"], ["초코크림롤", "132637"], ["도미미", "130926"], ["좌파", "130346"], ["트로엘", "128325"], ["Identical", "124867"], ["우호", "124432"], ["코레", "124118"], ["누눈", "123562"], ["Ferocious", "123073"], ["뮤디르", "121737"], ["이제운", "120189"], ["Ciel", "119686"], ["Tema", "119576"], ["정신못체리는맛", "117913"], ["로봇", "115378"], ["닌도리", "114541"], ["주광창", "113477"], ["록리", "112818"], ["이꿈소", "111742"], ["이설이", "103045"], ["이유하", "102761"], ["공운", "102699"], ["미오지오", "102274"], ["제이슨'토드'", "100132"], ["창백한밤식빵", "99977"], ["꾸웃", "97785"], ["하연", "95411"], ["차말", "95402"], ["챰치", "94661"], ["메챠쿠챠게형", "90935"], ["레리이즈", "87180"], ["아루시아", "86980"], ["묘아", "86106"], ["부들부들부들", "85881"], ["체셔캣", "85417"], ["라하야", "84205"], ["도미니언", "79006"]], "btn": [["호박왕", "1200889"], ["범현", "1073814"], ["Sajang", "1001805"], ["휘령", "1000926"], ["연어엉으어엉으엉엉", "996234"], ["에레이나", "940552"], ["비요소", "905966"], ["소트소트", "896769"], ["우주", "806884"], ["흰백짐승수백수니트", "806877"], ["찹쌀이", "801057"], ["에픽", "732648"], ["강장제", "722751"], ["잔디농사", "633217"], ["시스투스", "597295"], ["심평", "594332"], ["포포토", "503876"], ["자생", "500472"], ["망고스틴'", "490000"], ["교수님교수형", "434156"], ["기계북극곰", "373544"], ["엘주", "334792"], ["베네피라", "272784"], ["냥이메이드", "259876"], ["봉인된자의오른쪽발", "257454"], ["김춘팔", "256539"], ["와이어즈", "241165"], ["에스테르", "236040"], ["든세", "225155"], ["테노어", "224541"], ["Schema'", "224225"], ["나혼", "220602"], ["아이셰", "211038"], ["세피나르", "204672"], ["Identical", "203738"], ["깹띤", "200993"], ["Myoul", "183498"], ["디아카", "175101"], ["옵스크리타스", "171262"], ["바위너머", "164059"], ["Jerrie", "163708"], ["까만냉면", "162965"], ["풀맛", "161429"], ["티피피", "158086"], ["조이루즈", "154141"], ["트리셰", "145085"], ["백터맨이글", "142269"], ["푸파파파", "139351"], ["물밑어둠", "139093"], ["박과장", "133375"], ["체셔캣", "128507"], ["Marcel", "125025"], ["니츠케", "121265"], ["그랑프레스토", "120394"], ["김백화", "118707"], ["루크", "116608"], ["남익황", "115698"], ["우호", "115648"], ["마나르", "114097"], ["포기다", "109646"], ["김독자", "105426"], ["귀여운나를봐줘", "104260"], ["세상", "103271"], ["Brilliant", "102148"], ["미하루", "101964"], ["릴로", "101838"], ["나흘", "101745"], ["크리스텐", "100327"], ["다름", "100320"], ["유이시연", "100189"], ["박도혜", "96924"], ["해브", "94213"], ["키아리", "93984"], ["밤쿠쿠", "93902"], ["와와라고", "92548"], ["학자", "92306"], ["별파스타", "92234"], ["에르미앙스", "92067"], ["공맹도", "90004"], ["아기쿄끼", "89915"], ["늘솔", "88442"], ["Irian", "87973"], ["의홍", "87656"], ["유채", "86601"], ["샌즈위치", "86454"], ["올림", "86402"], ["히페", "86023"], ["금림", "82205"], ["신'시아", "82100"], ["포근", "81771"], ["제하'", "80325"], ["설찬", "79838"], ["타프", "78734"], ["미켈란젤료", "77148"], ["옷걸이", "77042"], ["Ferocious", "76325"], ["세이릭", "75548"], ["Ciel", "72621"], ["레리이즈", "72035"], ["메가실드", "70875"]], "fsh": [["욧슈이", "2216648"], ["단향기", "2092759"], ["메스테", "2033581"], ["신한", "2018805"], ["경찰", "2012168"], ["이웃집멍뭉", "2000842"], ["야옹하세요", "1920962"], ["담유", "1912868"], ["Hou", "1838704"], ["티오", "1830424"], ["의홍", "1811262"], ["라제시", "1789678"], ["데빗", "1769678"], ["제키엘", "1755138"], ["포포라", "1734989"], ["오르키누스", "1614823"], ["페페스트", "1614088"], ["움냠", "1524803"], ["튠버기", "1286538"], ["공오", "1163654"], ["시고르자브종", "1011688"], ["엘풍", "996563"], ["루헨", "850720"], ["원예사", "831509"], ["생새우초밥", "668489"], ["사리", "617279"], ["탱커만할겁니다", "602859"], ["사혁", "601206"], ["서술", "569043"], ["하현무", "568835"], ["본진터진애", "526630"], ["멜로롱", "506275"], ["Maramikhu", "503098"], ["석염", "501287"], ["갈색여우님", "458865"], ["Kimdobby", "441822"], ["앙갚음", "422200"], ["제콩", "398994"], ["란티스", "392049"], ["Kyle", "383185"], ["정화자하타르", "380434"], ["총장님", "377836"], ["달조각부엉이", "368840"], ["연두라", "362949"], ["제노스카이", "356891"], ["루텐텐웨이", "343732"], ["에버릿", "335844"], ["Heilou", "331667"], ["페리드", "323647"], ["세트", "323042"], ["김블리", "318797"], ["칼리번", "309707"], ["내신부", "309594"], ["푸른바다가재", "306569"], ["인제", "300283"], ["Kamoa", "293718"], ["장녀", "287685"], ["예즈람", "278858"], ["서낭", "277311"], ["Alex", "269595"], ["박판다", "260340"], ["랜킨", "259586"], ["미드가르드오름", "259101"], ["나도예쁜거알거든", "258645"], ["까오루", "250622"], ["Fourteen", "229684"], ["티아'", "225748"], ["Tatsuya", "219616"], ["이스텔라", "215776"], ["노하", "215373"], ["비디비디스", "214113"], ["희제", "211428"], ["여흔", "205955"], ["반다룬", "202846"], ["졔이", "202758"], ["프릴", "200000"], ["페니샤", "180350"], ["꿈속조상", "177109"], ["예림이", "174884"], ["야한세건", "169149"], ["카라쿠", "168941"], ["디로", "168897"], ["Herb", "166716"], ["밍종", "164641"], ["레벤우드", "162801"], ["낡은이", "154214"], ["사퍼점검언제끝나", "151404"], ["페루", "146118"], ["김남신", "142357"], ["류웨이", "141669"], ["호연백", "141629"], ["힘둥이", "136814"], ["헤파이톤", "136119"], ["극대화", "135266"], ["느을", "128489"], ["상은", "126163"], ["아몬드와호두두유", "120158"], ["김민초", "117952"], ["봉인된자의오른쪽발", "117114"], ["새유", "104256"]], "crp": [["림셔벗", "2626266"], ["Roze", "2495529"], ["어빈", "2000598"], ["붉은달", "1818170"], ["건하", "1812062"], ["과꽃", "1760776"], ["슈퍼잡초", "1650044"], ["챠티", "1585335"], ["진지한죠스바", "1549461"], ["레아메", "1530141"], ["꼬기", "1514152"], ["카르밀라", "1420310"], ["윤새강", "1390926"], ["하양이잇", "1355542"], ["엘라헤'", "1102417"], ["강민", "804328"], ["클릿클릿", "803028"], ["우유앙팡", "535648"], ["키아리", "503983"], ["장애물", "469085"], ["밥돌이", "444178"], ["니니아", "337021"], ["요정학입문", "336632"], ["메가실드", "300990"], ["버나미", "283929"], ["Azruine", "258479"], ["메핌", "208869"], ["박도혜", "207829"], ["호리애", "201247"], ["회오리감자", "162918"], ["아레인", "148954"], ["성직자", "140993"], ["타프", "124694"], ["빙둔", "117166"], ["티그리스", "114968"], ["오일파스퇴르", "110143"], ["엘가난", "108429"], ["야생의불곰", "107726"], ["알데바란", "103204"], ["뚜비둡", "102691"], ["공갈공갈", "100646"], ["렘피르", "92110"], ["제레미드쉬펠", "90379"], ["루제로", "90133"], ["하쿠온", "86321"], ["곱하기", "71476"], ["스트리비사", "70960"], ["Rubia", "69743"], ["카타크", "68997"], ["포엘라", "66740"], ["탄빵이", "62669"], ["두운", "59242"], ["톤토리", "59176"], ["라야라", "56829"], ["따뜻한핫초코", "56064"], ["신은삼", "53871"], ["리유니엘", "50488"], ["봉인된자의오른쪽발", "50138"], ["엘펜", "47367"], ["부겐빌레아", "44558"], ["Grahatia", "43232"], ["세피로트", "42913"], ["싹수", "35610"], ["로우스", "34430"], ["코다", "32968"], ["라라니르", "31864"], ["데이링", "30076"], ["다피르", "28217"], ["Mandarin", "26990"], ["아르샤빈", "24340"], ["셀라", "22742"], ["라니'", "22317"], ["아직덜자란", "21328"], ["영업부장", "21270"], ["폭주기관차", "20818"], ["애옹이귀여웡", "20587"], ["체아르", "20460"], ["샐비아", "19691"], ["Ding", "19560"], ["우주", "18997"], ["스케치북", "18764"], ["Sandg", "18413"], ["빛의동생", "18407"], ["단해", "18312"], ["레드포드", "17940"], ["Burnjjang", "17220"], ["테이르", "17131"], ["날뛰는사자", "16890"], ["북극곰살리기", "16321"], ["든세", "15740"], ["행구", "15285"], ["녹스", "15120"], ["쵸꼬비", "15028"], ["느을", "13005"], ["샤띠", "12580"], ["쥰'", "12205"], ["교수님교수형", "11656"], ["나르릉", "11656"], ["꾸루", "11518"], ["하낫", "11496"]], "bsm": [["김새해", "2440122"], ["우주먼지", "2000000"], ["트레오닌", "1754569"], ["냥코센세", "1716090"], ["천사", "1659027"], ["스타사파이어", "1617668"], ["오쯔", "1540868"], ["눌눌", "1516047"], ["너구루", "1373518"], ["코스트", "1370521"], ["아르딘", "1280787"], ["유별", "1191822"], ["우리집오르슈팡", "1140843"], ["한호", "1087315"], ["미르시류", "954287"], ["발로란", "754930"], ["하다르", "501117"], ["류에온", "500889"], ["연명", "414928"], ["레블란제", "312165"], ["Xenon", "300956"], ["참담한마음", "283978"], ["이오폴드", "281838"], ["떡둘떡셋", "278604"], ["보리밀", "273175"], ["너'구리", "266086"], ["고고슈", "250219"], ["딸기초코케이크", "249440"], ["모짜", "248480"], ["해인", "208384"], ["헤이든", "184024"], ["앙겔", "157871"], ["금지된언어", "153255"], ["단콩", "125316"], ["병아리", "125047"], ["Maramikhu", "110966"], ["쮸냥", "100654"], ["Clovis", "100445"], ["머스타드쏘쓰", "95833"], ["하현", "93655"], ["세르겔", "92642"], ["제레미드쉬펠", "92624"], ["머그", "90685"], ["야한세건", "89015"], ["렌타", "87803"], ["꾸루", "80101"], ["솔리티나", "72534"], ["백우", "71634"], ["힘을원하는가", "70980"], ["주노", "70213"], ["네프", "66714"], ["로저맥클로어", "66338"], ["떠뤼", "64926"], ["방랑객", "60840"], ["슈슈카", "59582"], ["에스키온", "58964"], ["휴양객", "58873"], ["메리딸기", "58118"], ["양근당파", "54104"], ["이원", "52569"], ["라야라", "52144"], ["이자성", "50831"], ["낸시'", "50057"], ["옥신", "48055"], ["아이크반츠", "43025"], ["필트오버", "39918"], ["로우스", "38501"], ["엔초", "37365"], ["하온부", "35286"], ["클릭", "34074"], ["파트릭", "32935"], ["명향", "32814"], ["해시", "32633"], ["슈니발렌'", "31516"], ["정남", "30292"], ["Louvre", "30000"], ["츄로", "27955"], ["스노우민트치즈빵", "24314"], ["봉인된자의오른쪽발", "24213"], ["셀라", "23088"], ["화이트아웃", "23071"], ["테이르", "21579"], ["택배업자", "21471"], ["다비흐", "21199"], ["내신부", "18950"], ["아케미", "18631"], ["엔쵸비", "17457"], ["쎄샤", "17373"], ["한밤", "17284"], ["오묘", "16834"], ["사리", "15647"], ["리피터", "15432"], ["Catherine", "14824"], ["린샤", "14793"], ["J'oritz", "12878"], ["연파랑", "12496"], ["봄사과", "12343"], ["아롱씨", "12321"], ["토미", "11707"], ["윤새강", "11463"]], "arm": [["환경", "3301111"], ["지언정", "2920952"], ["대길", "2550691"], ["은한", "2126714"], ["쿠프카", "2124984"], ["아롱씨", "2086886"], ["포이즌파이크", "2055542"], ["Ciel", "2035610"], ["카마인", "2002318"], ["테시엔", "1909229"], ["여름물고기", "1662386"], ["유리안", "1492202"], ["카스테라", "1255968"], ["스메", "1233395"], ["예그리나", "1077687"], ["유디스", "661331"], ["아이젠허트", "629107"], ["사야엔", "571417"], ["엘트라움", "501021"], ["Rux", "500079"], ["개인주의자선언", "384605"], ["리이이언", "375821"], ["곰구리", "373146"], ["루르", "356783"], ["템페라", "346800"], ["슈네르", "245006"], ["슴끈", "208922"], ["려아", "191067"], ["데드락", "183030"], ["시전", "182350"], ["가룬", "176935"], ["헤스티오", "171601"], ["반젤리스", "165228"], ["예송", "143723"], ["호방이", "141105"], ["히포", "139481"], ["처분", "129796"], ["재스", "127381"], ["졸려졸려졸려", "122424"], ["여셧", "107816"], ["제레미드쉬펠", "91361"], ["달모찌", "84799"], ["레몬늑대", "84681"], ["하량별", "82645"], ["베리펀치", "79410"], ["아루시아", "77511"], ["록리", "75007"], ["아르키노", "72395"], ["샤이엔", "70816"], ["미네크", "66451"], ["관광객", "65539"], ["카샤다라", "64138"], ["벨라모르테", "63374"], ["엘펜", "62641"], ["받건희", "61744"], ["서약", "58949"], ["서온", "56636"], ["블래키", "53591"], ["이꿈소", "52038"], ["비아트리스", "51374"], ["라야라", "51044"], ["아트반", "50458"], ["하연", "50230"], ["정맥", "50084"], ["양시백", "44295"], ["아르크'", "43142"], ["공급사슬", "43050"], ["마리", "42465"], ["주전하", "42270"], ["로우스", "39557"], ["민트초코빵", "36420"], ["말차라떼맨", "35602"], ["환멸님", "34903"], ["칼리스토", "34640"], ["도미네이터", "33875"], ["감로", "30302"], ["미드가르드오름", "29069"], ["Xianhe", "28650"], ["활호", "28169"], ["갈레트", "27545"], ["Catherine", "26622"], ["봉인된자의오른쪽발", "25642"], ["장드레", "25595"], ["손뚱", "24797"], ["제나시온", "23186"], ["아라니", "21008"], ["유병장수", "20309"], ["카르히나", "20017"], ["북극곰살리기", "19024"], ["윈첼", "18901"], ["Peep", "18064"], ["쿤도리", "17186"], ["코치", "16849"], ["켈피", "16110"], ["러브메", "16080"], ["란아", "16043"], ["루나리아", "15876"], ["모모하지", "15858"], ["할매", "15838"], ["Maehwa", "15505"]], "gsm": [["횸니", "2511907"], ["코코너엇", "2372660"], ["추릇", "2345679"], ["제타벤슨", "2233657"], ["크로니카", "1745621"], ["라이", "1675423"], ["트리셰", "1658454"], ["플라네타리움", "1640776"], ["푸피린", "1602242"], ["라테도령", "1480922"], ["냥일냥", "1411080"], ["뿔도저", "1336539"], ["유르페", "1331103"], ["Linne", "1304516"], ["셀크", "1254963"], ["티엔", "1227344"], ["콧김", "1180112"], ["오팔오팔", "1143656"], ["샤이엔", "710006"], ["로메릭비", "617154"], ["산돌지기", "583589"], ["솜쮸먹", "500999"], ["반달양파", "494062"], ["Maehwa", "385808"], ["폰폰", "325506"], ["아비터", "306251"], ["셋꼬등어", "233165"], ["코이'", "229816"], ["한나낭", "227391"], ["아르키노", "219396"], ["니아시", "188832"], ["월효", "185221"], ["후우라", "166440"], ["휴네", "163966"], ["루도비카", "150025"], ["하늘별", "149844"], ["태공", "130871"], ["이슈하", "124964"], ["길동군", "121854"], ["도냐도냐", "120048"], ["세세리", "111891"], ["아챌", "109035"], ["케일럽", "99322"], ["코코라이", "98155"], ["마일", "91304"], ["제레미드쉬펠", "88955"], ["필트오버", "88552"], ["루연", "88198"], ["거부기", "85510"], ["정의", "82338"], ["윤샤오", "80939"], ["근원", "74056"], ["힐줄랑말랑'", "73474"], ["야붕", "64958"], ["에고", "62521"], ["리넬", "62469"], ["시톨다", "56657"], ["Gisele", "54998"], ["라야라", "52602"], ["에클레르", "52526"], ["사야엔", "50931"], ["갓시", "50363"], ["페르디난드", "50036"], ["디다케", "47433"], ["르펠", "46545"], ["힘을원하는가", "46506"], ["메메타아", "45517"], ["운리어", "45262"], ["노각오이", "43483"], ["Delta", "40861"], ["연유'", "40191"], ["뮥'", "39102"], ["후레르랴", "38860"], ["Naegi", "36512"], ["끌레르", "35703"], ["오르비", "33458"], ["해파링", "32988"], ["시리우스", "32332"], ["모스버거", "31817"], ["진저에일", "31257"], ["서자", "31073"], ["나르니즘", "28765"], ["두당", "27030"], ["Elania", "26689"], ["절대널버리곤안가", "26514"], ["봉인된자의오른쪽발", "25181"], ["마녀", "23378"], ["아케미", "23326"], ["젤피", "22547"], ["꽃보다오베론", "22026"], ["오비우퐁", "20763"], ["코르와", "20000"], ["그윈돌린", "19747"], ["로우스", "19622"], ["글루틴", "18414"], ["김루안", "16348"], ["설악산티라미수", "16195"], ["잔몽", "16101"], ["문두비", "15894"], ["에델", "15772"]], "ltw": [["기능", "3138042"], ["빠른바람", "2882401"], ["멸살법최고권위자", "1867296"], ["Hwai", "1839488"], ["아뮬", "1791852"], ["알디네", "1643803"], ["렊끼", "1593699"], ["포디사디", "1581242"], ["아리엔", "1455331"], ["카쯔", "1451494"], ["라프란체", "1447777"], ["린드세이", "1426290"], ["팽태자", "1408507"], ["오밀조밀", "1330687"], ["레쓰비", "1309384"], ["네피로스", "1217517"], ["세피나르", "1091990"], ["풀맛", "803987"], ["옷걸이", "550353"], ["미루나무", "522808"], ["데드락", "406502"], ["티피피", "368796"], ["백터맨이글", "304890"], ["빅레드", "279706"], ["로로루", "274478"], ["무극", "273532"], ["츠읔", "267235"], ["다름", "256601"], ["벨리", "250562"], ["천흔", "241843"], ["별루", "238547"], ["민든이", "203496"], ["엘주", "202606"], ["피펫", "194340"], ["민식이", "183324"], ["피리", "180284"], ["쀼쮸", "180052"], ["Tlfhgk", "166851"], ["제하'", "156038"], ["광식", "145676"], ["라이젠데", "143990"], ["나이리프", "126835"], ["학자", "126755"], ["리온누", "123128"], ["희목", "120397"], ["숲바다", "111727"], ["샤리엔", "103455"], ["다날", "100219"], ["제레미드쉬펠", "94871"], ["교수님교수형", "87589"], ["비트", "84241"], ["애독", "73826"], ["이르이", "71788"], ["참치사라", "61300"], ["필트오버", "59051"], ["라야라", "56416"], ["물밑어둠", "54971"], ["Saladin", "53128"], ["하와이", "52998"], ["김엘비", "51596"], ["쵸'", "50690"], ["게브리엘", "48760"], ["사츠", "48126"], ["아스테", "46620"], ["안성한우", "44426"], ["먕두", "40814"], ["꾸루", "40481"], ["굴러가는행인", "40403"], ["봉인된자의오른쪽발", "37058"], ["이첸", "34736"], ["모모우", "31790"], ["째미", "31444"], ["리아이하", "31157"], ["트리스트람", "30086"], ["멍길이", "30017"], ["아케미", "28469"], ["Chu", "28335"], ["세읹", "27582"], ["윤리", "27417"], ["니킬", "25727"], ["달빛의세이아", "24271"], ["원예사", "24099"], ["해브", "24007"], ["셀런", "23830"], ["반후", "23324"], ["이엔티", "20521"], ["크하학", "19641"], ["주룩주룩", "19141"], ["이소욱", "18852"], ["정화자하타르", "17288"], ["돌고", "17238"], ["태림", "17228"], ["Rays", "17135"], ["Lanaya", "16325"], ["포기다", "16208"], ["아직덜자란", "15915"], ["챠무엘", "15893"], ["에레이나", "15051"], ["Jerrie", "14084"], ["릴로", "13865"]], "wvr": [["부지니", "2525252"], ["연모", "2101278"], ["옴니", "1653458"], ["로라링", "1637493"], ["디오브란도", "1545737"], ["요술", "1521022"], ["천기의티엔", "1501278"], ["투수왕김짱돌", "1356532"], ["시베이카", "1354871"], ["아이토", "1314411"], ["Melange", "1217547"], ["에다키아", "1188011"], ["도양", "1132177"], ["타타루", "1127980"], ["그론달", "1076354"], ["종자", "766303"], ["대홍단라라펠", "703890"], ["벨리체", "606513"], ["Maramikhu", "500702"], ["라텔리디아", "436367"], ["Yda", "419903"], ["타카", "334314"], ["세티스", "312897"], ["Angel", "250642"], ["프관", "249746"], ["감자두조각", "213062"], ["면세된'노차", "200343"], ["Dis'", "177073"], ["국부", "149338"], ["티어", "140608"], ["사처낭", "128458"], ["쿠뽀아리", "121151"], ["밤앙금", "109277"], ["응호", "106329"], ["열녀", "92533"], ["이나나시", "88518"], ["제레미드쉬펠", "84732"], ["리차", "84032"], ["영광", "80632"], ["Mong", "73831"], ["무위", "73694"], ["현재", "72960"], ["아이릭", "64140"], ["설악산티라미수", "60458"], ["애션", "59833"], ["망충이", "58059"], ["통치꽁조림", "57291"], ["라야라", "51309"], ["유가", "50055"], ["예즈람", "49351"], ["단령", "46302"], ["노다담", "41368"], ["이서밈", "38942"], ["도헤", "35953"], ["아고고스", "34776"], ["해피", "34658"], ["지찬", "34253"], ["사드", "31710"], ["악혈", "31303"], ["쿠스", "31257"], ["쿠죠죠타로", "30423"], ["다이브까지삼초", "30359"], ["폰폰", "27056"], ["암호천재", "26003"], ["평정", "25834"], ["멜량", "24994"], ["존명", "23799"], ["청안", "23779"], ["야로'", "23453"], ["얀백", "23169"], ["유자'", "22701"], ["신우", "22686"], ["아케미", "21678"], ["근원", "20855"], ["꾸루", "20442"], ["박명구", "20400"], ["봉인된자의오른쪽발", "20284"], ["힐러지망생", "20041"], ["블루메", "20040"], ["Dean'", "19154"], ["마타리", "18478"], ["아틸라카", "18412"], ["엘펜", "18092"], ["기한", "17957"], ["까만소금", "17280"], ["라이젠데", "17054"], ["레블란제", "16984"], ["멱이", "16643"], ["초황", "16193"], ["레코", "16014"], ["하날", "15845"], ["Myoul", "15690"], ["레니스", "15617"], ["은밀한모략가", "15430"], ["솜쮸먹", "14608"], ["구운붕어빵", "14546"], ["Lullaby", "14464"], ["심비연화", "13440"], ["빅토리아순덕", "13430"], ["Mercya", "13050"]], "alc": [["리오프", "2170855"], ["선공", "2091099"], ["레이사", "1765665"], ["타르헨", "1743365"], ["내꿈은춤신춤왕", "1695626"], ["제천", "1600735"], ["호'", "1600723"], ["Nuri", "1524441"], ["Issac", "1405826"], ["쳐비", "1366927"], ["김룬", "1338818"], ["바탕체", "1261392"], ["세이렝", "1237797"], ["Iviviviv", "1210451"], ["알론소웨버", "1104506"], ["섭힐", "953730"], ["김히리", "910368"], ["맥마나만", "882695"], ["하루샨", "623909"], ["미겔'", "578335"], ["프린클", "502380"], ["쪨리", "501711"], ["적진", "501183"], ["챰치", "500438"], ["Lemone", "424752"], ["세렌", "385189"], ["라포'", "358061"], ["라비타", "324318"], ["레오폴트", "317838"], ["세라'핌", "288644"], ["야룽", "267803"], ["이냥스", "242285"], ["날다", "238651"], ["히아님", "224471"], ["뭏냐", "215470"], ["루룬''", "210059"], ["류륭륭", "203102"], ["재야", "200386"], ["부들부들부들", "181876"], ["아리아드네", "178755"], ["달걀이추울때알파카", "172261"], ["산탄", "167103"], ["벤들라묭", "165494"], ["사카킷츠", "163664"], ["루현", "139835"], ["나좀봐주세요살려줘", "134484"], ["나우리", "130095"], ["방랑객", "117061"], ["키에", "115913"], ["케블리에", "115594"], ["제레미드쉬펠", "104933"], ["김춘추", "100078"], ["다담", "98415"], ["진이", "95449"], ["메이유리스", "94658"], ["허영", "93816"], ["고먐미냐냐옹", "93671"], ["샤르즈", "88868"], ["어이내외모를봐라", "87870"], ["Lada", "82512"], ["치카", "81961"], ["영숙", "80611"], ["멜리안", "79634"], ["일레인", "78520"], ["안디바", "77400"], ["새유", "77010"], ["힘을원하는가", "76350"], ["끌레르", "75930"], ["이담", "72853"], ["제나시온", "72177"], ["포겟", "70996"], ["마시로토모야", "68141"], ["Fluquor", "66054"], ["우간장", "64680"], ["코우지", "57850"], ["상어바", "56768"], ["라야라", "56329"], ["레이라스", "56225"], ["Zetta", "54014"], ["닌쟈", "53219"], ["유이시연", "53105"], ["네이렌", "52537"], ["쪼랭루루", "52115"], ["한나낭", "51053"], ["봉인된자의오른쪽발", "50760"], ["흐앙", "50621"], ["린샤", "48979"], ["파지래기", "45140"], ["므디", "43933"], ["Naru", "43433"], ["쿠'훌린", "41362"], ["셀라", "40344"], ["잔디농사", "38846"], ["두목음", "38727"], ["러브메", "35458"], ["시타'", "35361"], ["아케미", "31466"], ["Arcana", "29857"], ["레블란제", "29337"], ["주형", "28612"]], "cul": [["환멸님", "3074686"], ["코코라비", "2583687"], ["훤우님", "2233550"], ["봉인된자의오른쪽발", "2222222"], ["야노노", "2044476"], ["문한", "1865434"], ["총사", "1842464"], ["헤스티오", "1555652"], ["아지안", "1521461"], ["선우지태", "1318477"], ["테르라인", "1289999"], ["오르비", "1259031"], ["켈피", "1256460"], ["소다링", "1185749"], ["잔몽", "732082"], ["피에르", "707233"], ["허니욘", "662132"], ["상은", "633072"], ["아이프", "501974"], ["샘'", "389197"], ["감성", "358982"], ["트리아케", "347708"], ["교수형", "323344"], ["실량", "309703"], ["백사해", "262360"], ["밀리아", "231399"], ["리에페", "222220"], ["김좌", "220960"], ["린함펠만", "201313"], ["셕이", "200465"], ["Dana", "189185"], ["아몬드와호두두유", "184111"], ["예봄", "162566"], ["에즈라이", "161368"], ["미역싫어", "151828"], ["페트리슈", "150598"], ["빡빡츄", "135831"], ["나무꾼선녀", "121048"], ["우별", "120590"], ["퐁퐁팡", "118701"], ["윤이하", "109966"], ["댤고냐", "107657"], ["닉네임을변경하세요", "107081"], ["선우리", "106990"], ["르베누아", "104775"], ["베로", "104294"], ["녹챠", "100697"], ["제레미드쉬펠", "99221"], ["세이릭", "90491"], ["제리제", "87469"], ["백미이", "85291"], ["달보드레", "82861"], ["로건카시어스", "78051"], ["Melange", "73072"], ["카쯔", "72703"], ["에이엘", "67217"], ["라야라", "64364"], ["현지윤", "63895"], ["코카펩시", "58932"], ["새라밤", "58620"], ["멕시코갈매기", "55720"], ["뻬꼬기", "55042"], ["리제로테", "54214"], ["어둠의흑설탕도끼", "54182"], ["양말랑", "53103"], ["레모데'로즈", "53048"], ["루룬''", "52914"], ["퓨마", "51803"], ["다이치", "51565"], ["Paga", "50766"], ["항생제", "50032"], ["레리즈", "49484"], ["포엘라", "47708"], ["송파구핵주먹", "45642"], ["랑뉴", "44986"], ["환생", "44131"], ["Kaisser", "40075"], ["미네'", "39746"], ["Dazs", "39417"], ["코쿠룬", "38563"], ["Rux", "37350"], ["다비흐", "34862"], ["프뤼", "34854"], ["아이스와플", "31111"], ["로우스", "30205"], ["알페라", "29058"], ["냐에", "28836"], ["윤유월", "28649"], ["앤시어", "28081"], ["판나", "27012"], ["아일레르", "26769"], ["오르키누스", "25800"], ["양빵", "25473"], ["국부", "25252"], ["이재준", "24910"], ["묘운", "24851"], ["루칼리스", "24478"], ["싸부님", "24264"], ["알베리코", "22913"], ["Brilliant", "22320"]]}, "tonberry": {"min": [["에픠", "1378855"], ["마히", "1028783"], ["기린하넹", "1004000"], ["사과사각", "973557"], ["꽃가게", "861398"], ["김곤", "820404"], ["준우", "811238"], ["유아란님", "803529"], ["제제탄빵", "795168"], ["열망", "785170"], ["보리푸딩", "747642"], ["아스텔도리스", "746734"], ["라인란트", "703940"], ["모짜르트", "702270"], ["초새벽", "694320"], ["나토", "602910"], ["째구", "517674"], ["채작", "511065"], ["김세한", "482049"], ["슈피", "362926"], ["펩시유", "342489"], ["Kacha", "307087"], ["단려", "262913"], ["열예", "257296"], ["세니샤", "250519"], ["진궁", "227846"], ["이하세", "198608"], ["아라", "196986"], ["랄꺼", "196891"], ["코비", "186282"], ["모빌", "182680"], ["나기''", "181265"], ["연무", "180276"], ["노아칸", "172556"], ["추상", "167965"], ["샤트", "152905"], ["마티나'", "150474"], ["킹알마", "142469"], ["로고쉬", "135899"], ["Maylily", "133356"], ["눈토끼", "130906"], ["Lieutenan", "130593"], ["최규삼", "130295"], ["Equivocal", "121533"], ["이열화", "117059"], ["기린롤", "113419"], ["츄추", "105678"], ["이루다", "87993"], ["Helector", "84217"], ["백연호", "81889"], ["인테그", "81724"], ["Lucenera", "81406"], ["온새미로", "76534"], ["에클라", "74321"], ["이시윤", "72351"], ["로슈아", "69675"], ["크레이티", "69378"], ["대주주", "68721"], ["강다람", "67752"], ["팡야", "67735"], ["코류아", "67521"], ["단흑", "66294"], ["Bluesky", "65418"], ["뀨백", "61586"], ["테시미나", "61547"], ["사우지마세여", "60279"], ["백도벤", "60098"], ["슈텐", "58495"], ["왕도뇽롱", "55949"], ["백금'구피", "55399"], ["서제", "53884"], ["김벗다", "53278"], ["이렌샤", "52735"], ["환랑", "52479"], ["랭랭", "52457"], ["아닉", "51325"], ["음표", "51167"], ["일타강사치명타", "51109"], ["권여름", "51097"], ["희망꽃", "50214"], ["라베두크", "47202"], ["둥둥이집사", "47073"], ["비뉴", "43908"], ["오르쿠스", "43696"], ["곱셈추위", "43637"], ["유하람", "43384"], ["아르메", "43290"], ["제작", "42891"], ["제혁", "42649"], ["탁구리", "42196"], ["레이먼", "42014"], ["위형준", "41684"], ["Ressteroq", "41153"], ["똔꼬", "40626"], ["고링", "39789"], ["환예원", "39485"], ["Cococcc", "39480"], ["탄범", "39017"], ["듀듀몬", "39006"], ["발사자르", "37423"]], "btn": [["드보르작", "1115912"], ["은력", "1086877"], ["루티에", "1037028"], ["안개꽃", "988533"], ["사모페이", "954993"], ["쇼베른", "947699"], ["진저브레드", "931015"], ["Love", "924926"], ["히료", "924000"], ["럭걱", "923488"], ["고민중", "907771"], ["쿠뿌디쿠뿌", "905587"], ["냐구리", "898718"], ["김봄비", "882683"], ["Mute", "828170"], ["먕먀", "748367"], ["피오나아", "574962"], ["은려", "550150"], ["새볶", "473851"], ["김인장", "402871"], ["에쉐", "355500"], ["랄꺼", "338398"], ["Kooon", "323688"], ["프레디", "274281"], ["담백", "272491"], ["김세한", "260707"], ["코비", "236182"], ["임시우", "230952"], ["아라", "223532"], ["루네마", "217404"], ["몽윤", "186894"], ["Equivocal", "177991"], ["이렌샤", "171067"], ["강인하", "150293"], ["스파이", "150140"], ["십숑", "149647"], ["냥냥선생", "147837"], ["주일", "137910"], ["햇'감쟈", "137877"], ["나늘", "134051"], ["유엽화", "131815"], ["페라르", "130249"], ["웃픈아이", "128561"], ["여우깡", "119204"], ["슈크림냠", "117357"], ["은새", "107061"], ["견갑근", "101419"], ["비자", "101101"], ["난뻔뻔해", "100803"], ["수로", "98856"], ["댕뿌", "98377"], ["테서", "93928"], ["동원홈푸드", "93350"], ["연무", "91492"], ["탠지", "91264"], ["샤오", "89540"], ["아우렐", "89509"], ["나르게", "83753"], ["쿠키런", "80613"], ["작은얼음", "80199"], ["윤초신", "75742"], ["반애", "75570"], ["간잽이", "74599"], ["왕도뇽롱", "74006"], ["바생이는못말려", "73785"], ["파파야메론", "73291"], ["김찬", "73176"], ["탄마", "72608"], ["노아칸", "71460"], ["Lieutenan", "71435"], ["초현실주의", "66905"], ["미에즈", "65551"], ["꿈꾸는양", "65254"], ["잇플", "65195"], ["Gavin'", "64439"], ["김한지", "63574"], ["나시고렝", "63059"], ["망겜만해요", "61882"], ["니베이아'", "60856"], ["알로웬", "60025"], ["킹알마", "60021"], ["Teailreo", "59456"], ["곽짱박", "59400"], ["꽃가게", "59032"], ["천어훙", "58100"], ["따갭", "58083"], ["Kkaxi", "57814"], ["예다넬", "57321"], ["조연'", "56104"], ["스낵워터도그", "55802"], ["사워크림", "55600"], ["듀듀몬", "55217"], ["팡야", "54986"], ["도일", "54852"], ["오르쿠스", "54810"], ["숭아", "51189"], ["이재식", "51044"], ["해적냥", "50798"], ["문조", "50388"], ["쉐쉐아베리", "50305"]], "fsh": [["전장", "2207999"], ["쪼또", "1606646"], ["시흑", "1592974"], ["Sheryl", "1540535"], ["루키우스", "1422640"], ["니지히티", "1352529"], ["파새", "1248384"], ["Fischer", "1243671"], ["섹시함", "1234567"], ["연격", "1175616"], ["마틴'챌피", "1173442"], ["카앰", "1119056"], ["옹이", "1093361"], ["공주님'", "1068586"], ["때리지마요", "1042889"], ["월척", "918879"], ["얼음꽈배기", "502003"], ["믓채", "485385"], ["Niawhite", "423160"], ["츄파츕스'", "410647"], ["Houndfox", "372287"], ["Puretide", "360365"], ["콘다", "359404"], ["휴식", "335521"], ["현혁", "321484"], ["먼뎅", "300359"], ["백옥자", "257334"], ["육일", "240672"], ["리젠트걸", "214427"], ["퍄오란도", "210726"], ["울다하이장님", "207690"], ["보니따", "206431"], ["초록싹", "182374"], ["어는점", "177980"], ["매더", "174363"], ["초콜릿푸딩", "172328"], ["레기", "167075"], ["까만빛", "164889"], ["피가죽", "160860"], ["Kinney", "155394"], ["두푸", "149221"], ["양운", "143227"], ["후우카", "139418"], ["하얀뱀", "132994"], ["체리쿵야", "130792"], ["Priscila", "126572"], ["가래떡", "124009"], ["산호섬", "118996"], ["다루라나", "117831"], ["고사리무침", "115857"], ["브릴", "115768"], ["백도벤", "114181"], ["아닐걸요", "113165"], ["벽운", "109369"], ["형걔누구야", "108208"], ["따듯", "104057"], ["아드스텐", "103229"], ["뇸뮥", "101800"], ["미에즈", "100567"], ["웅냐흥냥", "99879"], ["치하키", "96544"], ["뚱땅뚱땅", "93192"], ["로잘린", "91967"], ["토구", "86706"], ["J''", "86607"], ["냐스미", "85441"], ["개옹", "84860"], ["설레아", "84678"], ["행방", "84472"], ["빡돌", "82945"], ["메리제인'", "81059"], ["힝프레드", "78787"], ["윤담", "75431"], ["김추석", "72960"], ["자메뷔", "71214"], ["봄옴", "70533"], ["뭐든알바아냐", "69169"], ["Sylvester", "67607"], ["별호", "67077"], ["칠흑'", "63299"], ["뮤게진", "61481"], ["강남동곽운조", "60057"], ["에카르테'란셰", "59833"], ["Usnim", "59559"], ["김쀼삡", "57805"], ["겜알못", "57638"], ["히지카타", "57070"], ["능글", "56085"], ["Miah", "55170"], ["달모래", "54257"], ["운후", "53131"], ["Airena", "52199"], ["닉닉", "51531"], ["달세뇨", "51483"], ["래오", "51112"], ["삼정", "48570"], ["테프샤", "46904"], ["듀레시", "45033"], ["Dil", "44759"], ["류기율", "44546"]], "crp": [["뒹구리", "2614543"], ["또비'", "2503668"], ["토마토", "1259221"], ["레뮤온", "1104233"], ["아이언사이드", "1000650"], ["노래하는냐냥", "979151"], ["현설", "935612"], ["도건'", "931784"], ["렌잘", "905221"], ["레이발렌틴", "831480"], ["열희", "815315"], ["세살치즈", "794446"], ["마테차", "780188"], ["다이사", "675569"], ["도량", "582587"], ["헤이르", "277275"], ["급구", "264271"], ["아아엉너", "218117"], ["언니걔누구야", "204916"], ["프레실라", "138881"], ["유윤오", "125846"], ["아르나'", "122698"], ["현홍", "94967"], ["피뽀", "91380"], ["바실", "91144"], ["Arysis", "86256"], ["수로", "83683"], ["세이시치", "79340"], ["냐하린", "78322"], ["초코맛쿠키", "70875"], ["신나리", "62093"], ["뭐든알바아냐", "59760"], ["프레디", "57863"], ["왕도뇽롱", "54026"], ["대학교수김우라", "51029"], ["김가평", "46100"], ["Dil", "45263"], ["루네마", "41768"], ["미륵궁예", "41361"], ["꼬블", "38583"], ["김이몬", "37855"], ["고은우", "37748"], ["반애", "37168"], ["티켓", "33256"], ["천어훙", "33115"], ["조연'", "32091"], ["합이", "31061"], ["박공주", "31049"], ["이크", "30536"], ["비선실세", "28116"], ["앨리스'", "25096"], ["도일", "23352"], ["오비야", "23030"], ["니베이아'", "22973"], ["가펭", "22535"], ["복뚠이", "22020"], ["해적냥", "22020"], ["티반", "21456"], ["무말", "21407"], ["칼날비", "20850"], ["팡팡도사", "20438"], ["대치동엘리자베스", "19202"], ["쉴리아테", "18665"], ["예다넬", "18410"], ["예사야", "16829"], ["도메스틱스", "16658"], ["문조", "16240"], ["연무", "16213"], ["요름", "16110"], ["달걀", "15875"], ["김똑딱", "15527"], ["Gavin'", "15259"], ["다임", "14933"], ["크아악미안해요", "14796"], ["라르망'디", "14198"], ["곽짱박", "13639"], ["촉촉젤리쥐", "13556"], ["악필", "13432"], ["암월의검", "13229"], ["Uagain", "13012"], ["Ramil", "11835"], ["Papillon'", "11597"], ["나늘", "11138"], ["쁘엉", "11100"], ["슈피", "10810"], ["루나린", "10642"], ["뮤링", "10486"], ["꽃집청년루드", "10403"], ["나른해", "10176"], ["테쓰", "10143"], ["곡물친구옥수수", "9668"], ["김이니", "9466"], ["주애", "9450"], ["이재식", "9231"], ["극선", "9180"], ["딸기찰떡", "8641"], ["민꼬", "8640"], ["메르세데스'", "8430"], ["초코안님", "8206"], ["사워크림", "8182"]], "bsm": [["그냥다내꺼", "1599076"], ["팡팡도사", "1205142"], ["두릅나무", "1157429"], ["프레키", "1011462"], ["뜛쓻똃쨞뀴", "1000519"], ["츄별", "945003"], ["단온", "929624"], ["호키노", "788248"], ["채태경", "780981"], ["삼촌걔누구야", "779964"], ["그리피스천문대", "714311"], ["따피", "634225"], ["먐뮴먐묨", "620791"], ["봉실", "617431"], ["신사동밥빙기", "556627"], ["셈티오", "403143"], ["김이니", "250276"], ["탈탈탈", "239033"], ["루르팡", "238894"], ["나말고힐러때려", "191903"], ["Fenwick", "144538"], ["서포터고수", "135050"], ["위긴", "134458"], ["Rangho", "113023"], ["물병", "101084"], ["구름구름봄", "77744"], ["사약", "67317"], ["로잘린", "66712"], ["사자친구", "64865"], ["리보땽", "63153"], ["영업", "63030"], ["Kooon", "53527"], ["에바임", "50955"], ["치혁", "50849"], ["리브레뉘", "47168"], ["탐험", "43481"], ["흑발정장안경남캐", "42165"], ["외르타", "37993"], ["가련", "35660"], ["클리드네프", "28773"], ["릭님", "26401"], ["뭐든알바아냐", "26240"], ["랭랭", "23910"], ["리햔", "23397"], ["큐프라이트", "22858"], ["볼짤", "22346"], ["프란시오타", "21576"], ["슈피", "21372"], ["네리아", "21083"], ["폼포뇸뇸", "18774"], ["K'shoua", "18599"], ["벨로체", "18527"], ["기다리다", "18507"], ["Meria", "18363"], ["타크사카", "17250"], ["열망", "16901"], ["유길리", "16719"], ["연무", "15646"], ["레오폴트", "15120"], ["사구파토", "14909"], ["센라", "13894"], ["Youth", "13735"], ["Cirdan", "13433"], ["저스틴준표", "12978"], ["Kal", "12262"], ["시니피에", "12212"], ["머우", "12116"], ["주민세가챠보다싸다", "12042"], ["교수''", "11640"], ["김벗다", "10437"], ["유리깃", "9900"], ["하른", "9229"], ["생갈치", "8983"], ["뉴케아", "8892"], ["심령", "8617"], ["개안", "7928"], ["라인비히", "7248"], ["젠틸레", "6977"], ["Dozer", "6458"], ["파샷", "6237"], ["일링크", "6150"], ["감쟈웅", "6142"], ["빤스", "6000"], ["뽐미", "5987"], ["카롱님", "5927"], ["선운", "5880"], ["초로인", "5352"], ["라이프제로", "5232"], ["Roco", "5145"], ["샤피레인", "5067"], ["테스타로사", "4800"], ["세나타", "4669"], ["지평", "4611"], ["수국", "4567"], ["가르간", "4514"], ["칠흑'", "4493"], ["세입자", "4383"], ["양비", "4351"], ["다이사", "4318"], ["오믈렛", "4014"]], "arm": [["모니챠", "2531282"], ["피치쿠션", "2250661"], ["라엘", "2226222"], ["네테에라", "1844086"], ["루루디", "1597768"], ["휘연", "1406602"], ["넝쿨", "1136625"], ["쌍검술고양이", "1091456"], ["티예", "908770"], ["능글", "862069"], ["엔라이", "712235"], ["헤이르", "557017"], ["단흑", "510514"], ["독타", "288187"], ["위렌", "239304"], ["빠키", "238086"], ["매자님", "234471"], ["Rass'", "230367"], ["Ressteroq", "211732"], ["강다람", "151677"], ["노아칸", "84483"], ["몜뮈", "78614"], ["에멤", "72069"], ["동굴", "71583"], ["탱쟈", "69994"], ["서리해바리", "62157"], ["마티나'", "51194"], ["해민", "46062"], ["고럐", "41266"], ["꽃집청년루드", "39734"], ["라히나", "30587"], ["Aporia", "28469"], ["마시쿤", "28436"], ["마찌", "28279"], ["슈텐", "26394"], ["별츄", "26343"], ["젤리토", "25950"], ["권은형", "25830"], ["오로라", "23865"], ["이츠", "23404"], ["노래하는냐냥", "21926"], ["Sosuki", "21705"], ["탄범", "21321"], ["피넨", "20336"], ["라베두크", "20100"], ["연무", "20034"], ["약삐삐", "18517"], ["로슈아", "18167"], ["귤까먹고싶다곰", "17802"], ["대주주", "17750"], ["곱셈추위", "16791"], ["크림홍차", "16663"], ["라체르", "16466"], ["진설", "15885"], ["릴링", "15771"], ["나혜", "15263"], ["토구", "15224"], ["이루다", "14817"], ["쬬랭", "14550"], ["디디빵조아", "13706"], ["로고쉬", "13643"], ["수예", "12681"], ["루마루", "12626"], ["카라멜마끼야또", "12030"], ["Comet", "11964"], ["희망꽃", "11957"], ["위형준", "11917"], ["바그너", "11880"], ["김옥분", "11689"], ["페니언", "10967"], ["라이얀", "10636"], ["아닐걸요", "10449"], ["밤비''", "10410"], ["토게토게", "10369"], ["한깸뜨자", "10018"], ["우뀨", "9857"], ["가경", "9720"], ["매더", "9718"], ["Coffee", "9390"], ["햇뿌", "9387"], ["아르메", "9187"], ["얼음꽈배기", "8984"], ["숨겨도뿌링클어쩌나", "8752"], ["개삼", "8704"], ["차희범", "8610"], ["홍심", "8354"], ["신사동밥빙기", "7937"], ["Mintz", "7800"], ["형아", "7710"], ["려훈", "7552"], ["츄추", "7376"], ["기브미쪼꼬래", "7337"], ["맹우의맹우", "7219"], ["슈피", "7111"], ["라이프제로", "6990"], ["남을돕고살아야지", "6955"], ["웅냐흥냥", "6771"], ["태리냥", "6630"], ["아나토제", "6176"], ["준호쨩", "6030"]], "gsm": [["두비'", "2345791"], ["비셸스", "1591590"], ["탱커버리기", "1583249"], ["달라란", "1532732"], ["사비'", "1387554"], ["본영", "1300086"], ["작별", "1160116"], ["페르세라피나", "1135757"], ["Straycat", "1003864"], ["달세뇨", "979577"], ["바다의밥도둑게딱지", "970176"], ["장모", "935891"], ["오믈렛", "928437"], ["흰비", "834413"], ["코움", "829337"], ["둥둥이집사", "471887"], ["단오'", "310806"], ["히지카타", "303543"], ["수'", "177208"], ["뀨백", "158736"], ["루나린", "136329"], ["유하람", "135480"], ["튀어", "133486"], ["강남동곽운조", "125197"], ["치와", "102908"], ["하늘연달", "95616"], ["살짝탄감자톤베리귓", "94783"], ["수정곰", "83798"], ["뿌꾸", "73259"], ["Gige", "70558"], ["아므엔", "66457"], ["엔라이", "64623"], ["크라스니", "64054"], ["사서애", "63733"], ["발레프", "62376"], ["참새님", "53706"], ["우신우", "51874"], ["제작", "45451"], ["호냐냣", "37842"], ["전대마왕", "35016"], ["루나사", "33637"], ["Aubert", "26390"], ["백문약", "26209"], ["K'shoua", "26073"], ["하르망", "25756"], ["어년", "22729"], ["보송보송말랑고양이", "20320"], ["Mirmani", "19967"], ["발사자르", "19104"], ["사우지마세여", "18209"], ["연무", "18137"], ["퓨나", "15657"], ["쿠들", "15271"], ["호림", "13583"], ["별님''", "13189"], ["메로르", "12911"], ["마티나'", "12663"], ["라큘리너스", "12256"], ["진타이위", "12145"], ["쿠레나이클라", "12000"], ["슈피", "11862"], ["Alrisha", "11460"], ["두번째달", "11067"], ["Sidrig", "10143"], ["컵밥", "9871"], ["삼정", "9573"], ["앨리스'", "9333"], ["섯버'", "8277"], ["봄결", "7797"], ["Ning", "7710"], ["샤샤미르", "7203"], ["뉴케아", "7193"], ["바바카람찬트", "6993"], ["밳사", "6823"], ["신사동밥빙기", "6690"], ["김녹자", "6657"], ["클로브", "6295"], ["다호", "6063"], ["아라네", "5910"], ["아우라", "5848"], ["호랴럇", "5837"], ["Senya", "5735"], ["세컨", "5680"], ["춘화''", "5630"], ["소호'", "5601"], ["삼묘", "5537"], ["촐랑", "5386"], ["로라나", "5375"], ["퓨이", "5316"], ["Roco", "5092"], ["프리미엄태양초", "5036"], ["무라비", "4959"], ["뜨나", "4898"], ["이람", "4580"], ["송재", "4533"], ["전망", "4437"], ["디디빵조아", "4419"], ["딸기꿀", "4149"], ["아드리안'블랙", "4049"], ["Ceius", "3938"]], "ltw": [["라쏘", "2213400"], ["스노아", "1718014"], ["케스티안", "1113831"], ["코빵", "1002227"], ["봄꽃'", "858543"], ["티라피", "817137"], ["현홍", "735806"], ["댕뿌", "696684"], ["벽랑", "662564"], ["하르망", "661688"], ["간잽이", "650426"], ["보끔묜", "629399"], ["Masmas", "601801"], ["디에리아", "600500"], ["혬혬", "568810"], ["카링", "261209"], ["탱쟈", "180877"], ["시르텔", "171312"], ["닉닉", "141086"], ["플로레", "129506"], ["희율", "102669"], ["꿈꾸는양", "97847"], ["별꼼", "94548"], ["이시읍", "92028"], ["해혼", "88916"], ["떡다리나무", "86668"], ["라플라스", "81690"], ["금현", "73239"], ["응큼물범", "70985"], ["느긋한가젤", "67635"], ["Peter'", "63932"], ["K'shoua", "58993"], ["냥냥선생", "54911"], ["유하람", "49930"], ["냐미냐미", "43054"], ["왕도뇽롱", "37624"], ["메르체'", "37370"], ["위스키럼주", "35062"], ["장월선", "33797"], ["샤오", "27843"], ["잇플", "27571"], ["아메팡", "27336"], ["탠지", "25526"], ["도겸", "24855"], ["김한지", "23909"], ["베냐", "22302"], ["Roco", "21202"], ["Dil", "20587"], ["로만'", "19981"], ["슈피", "19704"], ["스낵워터도그", "19230"], ["홍심", "17162"], ["연무", "16673"], ["이재식", "16530"], ["꽃집청년루드", "15473"], ["별짓함", "15174"], ["한나봉에이드", "14344"], ["사워크림", "12988"], ["천향아", "12713"], ["계회", "12469"], ["신사동밥빙기", "12398"], ["머찌", "12056"], ["담미", "10664"], ["염라님", "10200"], ["에르벤'", "9920"], ["몽윤", "9685"], ["호잇호이", "9597"], ["또마", "9133"], ["단설호", "8970"], ["이나라", "8850"], ["아는게엄서요", "8433"], ["섹시함", "8252"], ["Ac", "8210"], ["페이레타", "8186"], ["기다리다", "7932"], ["오쏘", "7826"], ["아라스틴", "7650"], ["오르테", "7448"], ["요시꼬", "7412"], ["뭐든알바아냐", "7117"], ["Kooon", "7066"], ["김인장", "7060"], ["말괄량이삐삐", "6750"], ["힐러할래요", "6551"], ["머윗잎요정", "6390"], ["라리시움", "6383"], ["희망꽃", "5981"], ["평일", "5974"], ["Ceius", "5914"], ["스파이", "5875"], ["티페리트", "5762"], ["따따", "5655"], ["마인루나", "5538"], ["흠냐밍냐", "5336"], ["태리냥", "5300"], ["라티셰아", "5190"], ["민꼬", "5104"], ["유엽화", "4910"], ["방패용사'", "4867"], ["아우렐", "4500"]], "wvr": [["시하'", "2500719"], ["나임", "1745113"], ["빛나는별", "1522407"], ["대장", "1304734"], ["온음표", "1261359"], ["이브나", "1105897"], ["젠젠", "1096464"], ["경유", "1051978"], ["크레이티", "1048419"], ["말랑말랑커피", "1019335"], ["혜니", "1003217"], ["뀨우울", "968541"], ["담별", "852682"], ["플루나", "807661"], ["우윤", "725732"], ["페펭귄", "570503"], ["윤심덕", "442957"], ["키르슈타리아", "426404"], ["피오코", "322153"], ["쥐님임", "280340"], ["호잇호이", "178714"], ["도부", "132512"], ["템아", "129889"], ["레고레고", "117169"], ["샤샤미르", "103523"], ["공주사이버대", "102274"], ["김혜율", "87653"], ["스트렐리치아", "65830"], ["자몽구름", "63185"], ["판맨", "60399"], ["심유", "58748"], ["바삭한둘리", "56016"], ["유우쥬", "54990"], ["메론주스", "54838"], ["테루엘", "54740"], ["이츠", "51833"], ["성냥팔이소녀", "51522"], ["딸기꿀", "51303"], ["나솔", "48828"], ["검거미", "47602"], ["나래진", "43818"], ["밤고먐미", "43813"], ["빡돌", "40374"], ["기업", "36226"], ["에바임", "33035"], ["도아", "32898"], ["백금'구피", "32656"], ["연무", "31843"], ["왕도뇽롱", "30610"], ["오르쿠스", "30000"], ["듀듀몬", "27891"], ["비어천", "26729"], ["삼손", "25709"], ["백은섭", "25613"], ["빵집청년깽이", "25406"], ["숭아", "24630"], ["말랑'", "24214"], ["진각", "22961"], ["딸기청", "22551"], ["운후", "22529"], ["쿼카가내발을물었어", "22200"], ["미우라테", "21733"], ["하무하무", "21480"], ["제혁", "21475"], ["연심", "20970"], ["테리어칸", "20409"], ["설하율", "20400"], ["브리넴", "20388"], ["알리야", "19888"], ["세르펜", "19802"], ["길환", "19683"], ["백야", "19562"], ["지나가던용사", "19495"], ["이랑코", "19200"], ["국화빵", "18933"], ["햄스터사진수집회장", "18512"], ["레나나", "18270"], ["Ceius", "18248"], ["하얀야옹이", "18002"], ["려''", "17688"], ["필력", "17648"], ["표고", "17234"], ["포플러", "17137"], ["앨리스'", "17010"], ["백도벤", "16665"], ["유한경", "16646"], ["미친건너겠지", "16623"], ["영제", "16428"], ["이렌샤", "14767"], ["희상", "14370"], ["다루라나", "14328"], ["하가을", "13750"], ["야센", "13658"], ["아스티스", "13599"], ["투인", "13010"], ["대주주", "12306"], ["아스텔'", "11994"], ["와랄라토텝", "11659"], ["냠미", "11530"], ["스페니", "11288"]], "alc": [["초승달'", "2883317"], ["흠냐밍냐", "2470769"], ["바사", "1784251"], ["가헨", "1287785"], ["O'd", "1261436"], ["초코나무숲맛", "1136546"], ["펩시유", "1018187"], ["Lovecraft", "1016887"], ["알렉스'", "992186"], ["키안", "968945"], ["청화란", "925162"], ["마루카", "840452"], ["헤이르", "503662"], ["L'umen", "407669"], ["해피엔딩", "352499"], ["편도함수", "273094"], ["힝프레드", "246987"], ["클링", "214214"], ["두비두밤", "210898"], ["김살걀", "200710"], ["감자농장", "143840"], ["핥쏘쓰", "128640"], ["백서팀장", "114797"], ["달모래", "111756"], ["다솜'", "110017"], ["윤생", "108516"], ["다린느", "107810"], ["백야", "105919"], ["세니샤", "96600"], ["도모", "92541"], ["쨔뭉", "90973"], ["달콘", "86974"], ["잉여베스트", "84591"], ["동원홈푸드", "80617"], ["혼례", "79218"], ["채태경", "67582"], ["아르메", "62199"], ["에쉐", "61328"], ["능이할수없다", "57739"], ["부녀회장", "50222"], ["달세뇨", "46976"], ["카링", "44650"], ["에바임", "44071"], ["죽겠네", "43765"], ["유비'", "40992"], ["사랑", "39148"], ["김싱", "38706"], ["메페타민", "37500"], ["손정하", "36667"], ["주은비", "33171"], ["연무", "30587"], ["아메네", "27048"], ["공탄", "26792"], ["프로키온", "26264"], ["딜왕", "26073"], ["동구", "25218"], ["아닉", "24206"], ["세레브", "24086"], ["하현달", "22706"], ["몽귤", "22156"], ["레이먼", "21607"], ["트로바", "21442"], ["샤피레인", "21142"], ["백문약", "20968"], ["무조의", "20927"], ["츄추", "20386"], ["헤리그온", "18668"], ["Equivocal", "18660"], ["테시미나", "18173"], ["비세", "18066"], ["Ceius", "17720"], ["류큐", "17631"], ["다이사", "17597"], ["젠틸레", "17102"], ["재견", "16984"], ["경유", "16592"], ["무용무용", "16439"], ["Milktea", "16154"], ["기브미쪼꼬래", "16002"], ["슈피", "15935"], ["Helector", "15407"], ["금현", "15254"], ["넝쿨", "15227"], ["리이자몽", "15198"], ["술퍼먹고네발로기어", "14516"], ["학사경고", "14259"], ["꽃님이요", "14237"], ["K'shoua", "14153"], ["뫄니", "13950"], ["나기''", "13455"], ["나혜", "13357"], ["백연호", "13350"], ["강구'", "12923"], ["앨리스'", "12832"], ["러브앤피스", "12555"], ["떼분", "12476"], ["꼬부기'", "12332"], ["강남동곽운조", "12263"], ["바세린'", "11783"], ["토실토실", "11400"]], "cul": [["애오", "1571275"], ["다팍이", "1386387"], ["리얼케인", "1249529"], ["Nanoa", "1103844"], ["산하''", "1060937"], ["은새", "1024786"], ["설레아", "1006241"], ["불장난", "764804"], ["사랑", "726242"], ["얼룩꽁", "707389"], ["사탕요정", "617182"], ["정제", "444081"], ["떼분", "207078"], ["슈크림냠", "206967"], ["단청화", "163524"], ["보끔뱝", "161550"], ["가에", "157342"], ["셸레스트", "144985"], ["유하람", "143864"], ["아슈타드'", "135767"], ["루니''", "135617"], ["Roco", "107778"], ["백택", "100373"], ["빛봄", "90645"], ["기피", "83386"], ["에데니아", "75765"], ["신하", "68892"], ["하얀후추", "68031"], ["양시운", "60155"], ["에바임", "53908"], ["Kirito''", "50538"], ["뚜뚜따따", "50220"], ["냥냥애옹", "47376"], ["여건", "39758"], ["준호쨩", "37678"], ["꺾인꽃", "37321"], ["태후", "34769"], ["현표", "34217"], ["토선생", "33173"], ["Lieutenan", "32820"], ["그란돈", "30361"], ["제발살려주세요", "28053"], ["강등", "25563"], ["연겸", "21110"], ["네레데이스", "20862"], ["삐닉", "20658"], ["틱텍톡루카", "20011"], ["리우리엔", "18690"], ["화가많은전사", "18264"], ["신사동밥빙기", "17717"], ["유향루", "17614"], ["Lloyd", "16982"], ["아넬로에", "16902"], ["비람", "16629"], ["연무", "16333"], ["별호", "16121"], ["꼬마콩양", "14807"], ["Helector", "14097"], ["제''", "13500"], ["랑아야", "13408"], ["엄지공주최홍만", "12983"], ["데장군", "12796"], ["고냥어", "12656"], ["마시말랑", "12409"], ["슈피", "12409"], ["소록", "12366"], ["고운'", "12270"], ["서치원", "12232"], ["까까조아해여", "11653"], ["아르센'", "11528"], ["츄서방", "11516"], ["청색윤회", "11477"], ["유니콘퍄퍄", "10830"], ["그리피스천문대", "10706"], ["루나린", "10589"], ["까망이우다다", "10550"], ["Ahbo", "10082"], ["쿠로이르", "9725"], ["타타엘", "9720"], ["맛살", "8878"], ["I'ru", "8762"], ["낼룸'", "8070"], ["광희", "7842"], ["키타라", "7680"], ["평일의분노", "7657"], ["테수", "7597"], ["극셋", "7526"], ["김이니", "6987"], ["Dil", "6745"], ["디어메르헨", "6704"], ["궤궤", "6600"], ["라라신비", "6584"], ["희망꽃", "5991"], ["플뤼", "5791"], ["앞집까마귀", "5645"], ["Alrisha", "5560"], ["레베르나", "5389"], ["윤담", "5290"], ["스페니", "5199"], ["란단토", "5001"]]}}